{
  "summary": {
    "total": 1707,
    "pass": 1616,
    "fail": 91,
    "pass_rate": 94.67
  },
  "grp_stats": {
    "热线一组": {
      "质检量": 202,
      "差错量": 5,
      "通过率": 97.52
    },
    "热线二组": {
      "质检量": 193,
      "差错量": 4,
      "通过率": 97.93
    },
    "热线三组": {
      "质检量": 266,
      "差错量": 18,
      "通过率": 93.23
    },
    "热线四组": {
      "质检量": 209,
      "差错量": 7,
      "通过率": 96.65
    },
    "热线五组": {
      "质检量": 213,
      "差错量": 14,
      "通过率": 93.43
    },
    "热线六组": {
      "质检量": 171,
      "差错量": 17,
      "通过率": 90.06
    },
    "热线七组": {
      "质检量": 256,
      "差错量": 12,
      "通过率": 95.31
    },
    "热线八组": {
      "质检量": 197,
      "差错量": 14,
      "通过率": 92.89
    }
  },
  "records": [
    {
      "姓名": "穆琪",
      "组别": "热线三组",
      "质检评分": 80,
      "最近复检时间": "2026-06-04",
      "场景": "其他还款方式咨询",
      "整单评论": "[2026-06-04 14:38:23]王明卫:【质检差错】客户账单需对公还款，坐席发送对公账户和对公短链，引导客户对公还款，核实客户是渤海信托（蓝海）账单，需操作回购后才支持对公还款，坐席未申请回购，遗漏关键步骤\n【质检判罚】遗漏关键步骤-遗漏关键步骤：客户反馈的问题，按照SOP需要多个步骤进行判断或处理，客服遗漏关键步骤、错误处理或跳步骤执行，影响问题解决或处理",
      "单句评论": "-",
      "日期": "2026-06-04",
      "差错类型": "遗漏关键步骤",
      "差错描述": "客户账单需对公还款，坐席发送对公账户和对公短链，引导客户对公还款，核实客户是渤海信托（蓝海）账单，需操作回购后才支持对公还款，坐席未申请回购，遗漏关键步骤",
      "判罚内容": "遗漏关键步骤-遗漏关键步骤：客户反馈的问题，按照SOP需要多个步骤进行判断或处理，客服遗漏关键步骤、错误处理或跳步骤执行，影响问题解决或处理"
    },
    {
      "姓名": "王嘉乐",
      "组别": "热线五组",
      "质检评分": 80,
      "最近复检时间": "2026-06-04",
      "场景": "协商还款",
      "整单评论": "[2026-06-04 16:04:39]刘倩:【质检差错】账单逾期一天，客服协助减免逾期费用，小结单应该选择：未结清账单费率不满。 【质检判罚】问题分类选择错误-客服未按客户问题场景选择合适准确的小结单分类或工单分类。",
      "单句评论": "-",
      "日期": "2026-06-04",
      "差错类型": "问题分类选择错误",
      "差错描述": "账单逾期一天，客服协助减免逾期费用，小结单应该选择：未结清账单费率不满。",
      "判罚内容": "问题分类选择错误-客服未按客户问题场景选择合适准确的小结单分类或工单分类。"
    },
    {
      "姓名": "何海艳",
      "组别": "热线三组",
      "质检评分": 80,
      "最近复检时间": "2026-06-04",
      "场景": "逾期客户延期还款",
      "整单评论": "[2026-06-04 14:28:55]潘小佩:【质检差错】账单逾期申请停催，应转接给贷后转接组，错误转接给常规转接组\n【质检判罚】不应升但升/不应转但转-不应转但转：按业务 SOP 应自闭环场景，或不满足转接条件，客服错误转接（在线特例：在线坐席之间相互转接双判）\n",
      "单句评论": "-",
      "日期": "2026-06-04",
      "差错类型": "不应升但升/不应转但转",
      "差错描述": "账单逾期申请停催，应转接给贷后转接组，错误转接给常规转接组",
      "判罚内容": "不应升但升/不应转但转-不应转但转：按业务 SOP 应自闭环场景，或不满足转接条件，客服错误转接（在线特例：在线坐席之间相互转接双判）"
    },
    {
      "姓名": "赵晓莹",
      "组别": "热线五组",
      "质检评分": 80,
      "最近复检时间": "2026-06-04",
      "场景": "结清账单费率不满",
      "整单评论": "[2026-06-04 17:32:54]潘小佩:【质检差错】催促问题处理，沟通转接，未在处理中工单备注\n【质检判罚】关键信息记录错误-客服在联络记录/工单内容/处理结果中，存在信息记录不准确或未记录的情况，且可能会影响后续客户问题的处理\n",
      "单句评论": "-",
      "日期": "2026-06-04",
      "差错类型": "关键信息记录错误",
      "差错描述": "催促问题处理，沟通转接，未在处理中工单备注",
      "判罚内容": "关键信息记录错误-客服在联络记录/工单内容/处理结果中，存在信息记录不准确或未记录的情况，且可能会影响后续客户问题的处理"
    },
    {
      "姓名": "张梦欣",
      "组别": "热线八组",
      "质检评分": 80,
      "最近复检时间": "2026-06-04",
      "场景": "超级会员取消",
      "整单评论": "[2026-06-04 16:59:20]潘小佩:【质检差错】退好借卡+超级会员，坐席小结单未记录退超级会员问题\n【质检判罚】关键信息记录错误-客服在联络记录/工单内容/处理结果中，存在信息记录不准确或未记录的情况，且可能会影响后续客户问题的处理\n",
      "单句评论": "-",
      "日期": "2026-06-04",
      "差错类型": "关键信息记录错误",
      "差错描述": "退好借卡+超级会员，坐席小结单未记录退超级会员问题",
      "判罚内容": "关键信息记录错误-客服在联络记录/工单内容/处理结果中，存在信息记录不准确或未记录的情况，且可能会影响后续客户问题的处理"
    },
    {
      "姓名": "周灿",
      "组别": "热线一组",
      "质检评分": 80,
      "最近复检时间": "2026-06-04",
      "场景": "协商还款",
      "整单评论": "[2026-06-04 13:39:22]潘小佩:【质检差错】催促问题回电，处理中工单未备注\n【质检判罚】关键信息记录错误-客服在联络记录/工单内容/处理结果中，存在信息记录不准确或未记录的情况，且可能会影响后续客户问题的处理\n",
      "单句评论": "-",
      "日期": "2026-06-04",
      "差错类型": "关键信息记录错误",
      "差错描述": "催促问题回电，处理中工单未备注",
      "判罚内容": "关键信息记录错误-客服在联络记录/工单内容/处理结果中，存在信息记录不准确或未记录的情况，且可能会影响后续客户问题的处理"
    },
    {
      "姓名": "刘越美",
      "组别": "热线四组",
      "质检评分": 80,
      "最近复检时间": "2026-06-04",
      "场景": "协商还款",
      "整单评论": "[2026-06-04 13:42:58]段林涛:【质检差错】客户进线协商还款已经起诉，要求撤诉，坐席告知已经进入法诉阶段，引导与对方协商，客户未认可挂机坐席未建单升级处理；法诉用户需建单贷后处理（贷后系统核实该客户确实已进入法诉）；\n【质检判罚】应升未升：按业务 SOP 应升级场景，客服未创建升级工单",
      "单句评论": "[2026-06-04 13:36:55]段林涛:1",
      "日期": "2026-06-04",
      "差错类型": "应升未升",
      "差错描述": "客户进线协商还款已经起诉，要求撤诉，坐席告知已经进入法诉阶段，引导与对方协商，客户未认可挂机坐席未建单升级处理；法诉用户需建单贷后处理（贷后系统核实该客户确实已进入法诉）；",
      "判罚内容": "应升未升：按业务 SOP 应升级场景，客服未创建升级工单"
    },
    {
      "姓名": "张梦欣",
      "组别": "热线八组",
      "质检评分": 80,
      "最近复检时间": "2026-06-04",
      "场景": "好借卡取消",
      "整单评论": "[2026-06-04 14:45:51]王明卫:【质检差错】客户咨询69扣款核实告知好借卡扣款，客户需退费，协助处理退费，沟通中客户查询其他权益卡开通记录，坐席核实告知还有好借卡和超级会员，协助操作退费，且客户咨询放款失败问题，坐席解释告知，小结单联络备注未记录客户查询其他权益卡坐席协助退费和咨询放款失败问题，客户问题记录不完整\n【质检判罚】关键信息记录错误-关键信息记录错误：客服在联络记录/工单内容/处理结果中，存在信息记录不准确或未记录的情况，且可能会影响后续客户问题的处理",
      "单句评论": "[2026-06-04 12:13:45]王明卫:咨询放款失败问题\n[2026-06-04 14:41:25]王明卫:超级会员退费",
      "日期": "2026-06-04",
      "差错类型": "关键信息记录错误",
      "差错描述": "客户咨询69扣款核实告知好借卡扣款，客户需退费，协助处理退费，沟通中客户查询其他权益卡开通记录，坐席核实告知还有好借卡和超级会员，协助操作退费，且客户咨询放款失败问题，坐席解释告知，小结单联络备注未记录客户查询其他权益卡坐席协助退费和咨询放款失败问题，客户问题记录不完整",
      "判罚内容": "关键信息记录错误-关键信息记录错误：客服在联络记录/工单内容/处理结果中，存在信息记录不准确或未记录的情况，且可能会影响后续客户问题的处理"
    },
    {
      "姓名": "杨媛",
      "组别": "热线六组",
      "质检评分": 80,
      "最近复检时间": "2026-06-04",
      "场景": "好借卡咨询",
      "整单评论": "[2026-06-04 14:35:37]段林涛:【质检差错】客户进线要求取消好借卡自动续费，坐席引导告知关闭，沟通中无查询诉求仅关闭会员续费，小结单需点选“增值服务-好借卡取消”，坐席错选好借卡咨询；\n【质检判罚】问题分类选择错误：客服未按客户问题场景选择合适准确的小结单分类或工单分类。",
      "单句评论": "[2026-06-04 14:33:34]段林涛:1",
      "日期": "2026-06-04",
      "差错类型": "问题分类选择错误",
      "差错描述": "客户进线要求取消好借卡自动续费，坐席引导告知关闭，沟通中无查询诉求仅关闭会员续费，小结单需点选“增值服务-好借卡取消”，坐席错选好借卡咨询；",
      "判罚内容": "问题分类选择错误：客服未按客户问题场景选择合适准确的小结单分类或工单分类。"
    },
    {
      "姓名": "史磊磊",
      "组别": "热线二组",
      "质检评分": 80,
      "最近复检时间": "2026-06-04",
      "场景": "投诉催收作业",
      "整单评论": "[2026-06-04 11:48:28]潘小佩:【质检差错】非注册号码进线投诉催收，验证码无法核验，建议客户注册号码进线，小结单应为催收投诉安抚，坐席错选投诉催收作业\n【质检判罚】问题分类选择错误-客服未按客户问题场景选择合适准确的小结单分类或工单分类\n",
      "单句评论": "-",
      "日期": "2026-06-04",
      "差错类型": "问题分类选择错误",
      "差错描述": "非注册号码进线投诉催收，验证码无法核验，建议客户注册号码进线，小结单应为催收投诉安抚，坐席错选投诉催收作业",
      "判罚内容": "问题分类选择错误-客服未按客户问题场景选择合适准确的小结单分类或工单分类"
    },
    {
      "姓名": "张思婕",
      "组别": "热线八组",
      "质检评分": 80,
      "最近复检时间": "2026-06-03",
      "场景": "-",
      "整单评论": "[2026-06-03 14:23:42]段林涛:【质检差错】回电给客户退权益卡，坐席未保存小结单，全员群未报备有异常；\n【质检判罚】问题分类选择错误：客服未按客户问题场景选择合适准确的小结单分类或工单分类。若智能落单推荐的小结单或工单分类不准确，需手动选择符合客户问题场景的分类，直接选择推荐分类需扣罚",
      "单句评论": "-",
      "日期": "2026-06-03",
      "差错类型": "问题分类选择错误",
      "差错描述": "回电给客户退权益卡，坐席未保存小结单，全员群未报备有异常；",
      "判罚内容": "问题分类选择错误：客服未按客户问题场景选择合适准确的小结单分类或工单分类。若智能落单推荐的小结单或工单分类不准确，需手动选择符合客户问题场景的分类，直接选择推荐分类需扣罚"
    },
    {
      "姓名": "何海艳",
      "组别": "热线三组",
      "质检评分": 80,
      "最近复检时间": "2026-06-03",
      "场景": "催收投诉安抚",
      "整单评论": "[2026-06-03 16:08:20]刘倩:【质检判罚】客户投诉催收威胁恐吓，爆通讯录，客服解释催收规则，一直告知会核实催收问题规范流程，并会记录备注，强安抚未建单。 【质检判罚】应升未升/应转未转-应升未升：按业务 SOP 应升级场景，客服未创建升级工单",
      "单句评论": "-",
      "日期": "2026-06-03",
      "差错类型": "应升未升/应转未转",
      "差错描述": "-",
      "判罚内容": "客户投诉催收威胁恐吓，爆通讯录，客服解释催收规则，一直告知会核实催收问题规范流程，并会记录备注，强安抚未建单。 【质检判罚】应升未升/应转未转-应升未升：按业务 SOP 应升级场景，客服未创建升级工单"
    },
    {
      "姓名": "王嘉乐",
      "组别": "热线五组",
      "质检评分": 80,
      "最近复检时间": "2026-06-03",
      "场景": "结清账单费率不满",
      "整单评论": "[2026-06-03 14:11:35]王明卫:【质检差错】客户进线咨询费用不满问题处理进度，安抚不认可，在线转接处理，有处理中的费率不满工单未备注\n【质检判罚】关键信息记录错误-关键信息记录错误：客服在联络记录/工单内容/处理结果中，存在信息记录不准确或未记录的情况，且可能会影响后续客户问题的处理",
      "单句评论": "-",
      "日期": "2026-06-03",
      "差错类型": "关键信息记录错误",
      "差错描述": "客户进线咨询费用不满问题处理进度，安抚不认可，在线转接处理，有处理中的费率不满工单未备注",
      "判罚内容": "关键信息记录错误-关键信息记录错误：客服在联络记录/工单内容/处理结果中，存在信息记录不准确或未记录的情况，且可能会影响后续客户问题的处理"
    },
    {
      "姓名": "张思婕",
      "组别": "热线八组",
      "质检评分": 80,
      "最近复检时间": "2026-06-03",
      "场景": "催收投诉安抚",
      "整单评论": "[2026-06-03 14:21:55]潘小佩:【质检差错】申请停催，明天还款，未抱怨/投诉催收，小结单应为逾期延期还款，坐席错选催收投诉安抚\n【质检判罚】问题分类选择错误-客服未按客户问题场景选择合适准确的小结单分类或工单分类\n",
      "单句评论": "-",
      "日期": "2026-06-03",
      "差错类型": "问题分类选择错误",
      "差错描述": "申请停催，明天还款，未抱怨/投诉催收，小结单应为逾期延期还款，坐席错选催收投诉安抚",
      "判罚内容": "问题分类选择错误-客服未按客户问题场景选择合适准确的小结单分类或工单分类"
    },
    {
      "姓名": "刘浩",
      "组别": "热线三组",
      "质检评分": 80,
      "最近复检时间": "2026-06-04",
      "场景": "未结清账单费率不满",
      "整单评论": "[2026-06-04 17:52:38]杨姿娇:【质检差错】客户进线时，有处理中未结清账单费率不满工单，坐席未追加备注\n【质检判罚】关键信息记录错误-客服在工单内容中，存在信息记录不准确的情况",
      "单句评论": "-",
      "日期": "2026-06-04",
      "差错类型": "关键信息记录错误",
      "差错描述": "客户进线时，有处理中未结清账单费率不满工单，坐席未追加备注",
      "判罚内容": "关键信息记录错误-客服在工单内容中，存在信息记录不准确的情况"
    },
    {
      "姓名": "王嘉乐",
      "组别": "热线五组",
      "质检评分": 80,
      "最近复检时间": "2026-06-02",
      "场景": "账单查询",
      "整单评论": "[2026-06-02 14:57:12]潘小佩:【质检差错】客户进线反馈自己之前号码打不进来客服电话，怀疑平台拉黑了自己，最后客户再次纠结此问题，坐席告知客户短时间内多次进线的话他可能会有一些阻止，解答有误，目前未通知有此流程，如客户打不进来可建议客户换时间致电/解释咨询人数较多，不可按坐席解答告知，避免引起客户外诉\n【质检判罚】解答错误-客户进线反馈的问题，客服错误处理或提供不准确的解决方案，导致未解决或未覆盖客户的问题；或未按照SOP准流程执行，处理不全/错误，包括但不限于：产品规则解答错误、政策条款解答错误、操作指引介绍错误及信息数据回复错误等\n",
      "单句评论": "[2026-06-02 14:53:14]潘小佩:短时间内多次进线的话他可能会有一些阻止",
      "日期": "2026-06-02",
      "差错类型": "解答错误",
      "差错描述": "客户进线反馈自己之前号码打不进来客服电话，怀疑平台拉黑了自己，最后客户再次纠结此问题，坐席告知客户短时间内多次进线的话他可能会有一些阻止，解答有误，目前未通知有此流程，如客户打不进来可建议客户换时间致电/解释咨询人数较多，不可按坐席解答告知，避免引起客户外诉",
      "判罚内容": "解答错误-客户进线反馈的问题，客服错误处理或提供不准确的解决方案，导致未解决或未覆盖客户的问题；或未按照SOP准流程执行，处理不全/错误，包括但不限于：产品规则解答错误、政策条款解答错误、操作指引介绍错误及信息数据回复错误等"
    },
    {
      "姓名": "穆琪",
      "组别": "热线三组",
      "质检评分": 80,
      "最近复检时间": "2026-06-02",
      "场景": "协商还款",
      "整单评论": "[2026-06-02 14:24:50]王明卫:【质检差错】客户进线反馈减免还款问题，和工作人员协商减免的是5月7号账单，但工作人员操作减免的是6月1号账单，坐席告知问题处理中催促一下，有处理中的协商还款工单未备注\n【质检判罚】关键信息记录错误-关键信息记录错误：客服在联络记录/工单内容/处理结果中，存在信息记录不准确或未记录的情况，且可能会影响后续客户问题的处理",
      "单句评论": "-",
      "日期": "2026-06-02",
      "差错类型": "关键信息记录错误",
      "差错描述": "客户进线反馈减免还款问题，和工作人员协商减免的是5月7号账单，但工作人员操作减免的是6月1号账单，坐席告知问题处理中催促一下，有处理中的协商还款工单未备注",
      "判罚内容": "关键信息记录错误-关键信息记录错误：客服在联络记录/工单内容/处理结果中，存在信息记录不准确或未记录的情况，且可能会影响后续客户问题的处理"
    },
    {
      "姓名": "穆琪",
      "组别": "热线三组",
      "质检评分": 80,
      "最近复检时间": "2026-06-02",
      "场景": "超级会员取消",
      "整单评论": "[2026-06-02 14:31:22]潘小佩:【质检差错】客户表示自己没下载好分期APP，没订购会员被扣费199，坐席给客户解释，可能好分期平台有其他合作方，你在合作方那边误触了，解答有误，实际是客户2026-03-05办理的季卡是自动续费，所以到期扣费了\n【质检判罚】解答错误-客户进线反馈的问题，客服错误处理或提供不准确的解决方案，导致未解决或未覆盖客户的问题；或未按照SOP准流程执行，处理不全/错误，包括但不限于：产品规则解答错误、政策条款解答错误、操作指引介绍错误及信息数据回复错误等\n",
      "单句评论": "[2026-06-02 14:31:27]潘小佩:解答错误",
      "日期": "2026-06-02",
      "差错类型": "解答错误",
      "差错描述": "客户表示自己没下载好分期APP，没订购会员被扣费199，坐席给客户解释，可能好分期平台有其他合作方，你在合作方那边误触了，解答有误，实际是客户2026-03-05办理的季卡是自动续费，所以到期扣费了",
      "判罚内容": "解答错误-客户进线反馈的问题，客服错误处理或提供不准确的解决方案，导致未解决或未覆盖客户的问题；或未按照SOP准流程执行，处理不全/错误，包括但不限于：产品规则解答错误、政策条款解答错误、操作指引介绍错误及信息数据回复错误等"
    },
    {
      "姓名": "黄晓纯",
      "组别": "热线四组",
      "质检评分": 80,
      "最近复检时间": "2026-06-02",
      "场景": "协商还款",
      "整单评论": "[2026-06-02 14:09:41]潘小佩:【质检差错】有处理中贷后二线工单，坐席未备注\n【质检判罚】关键信息记录错误-客服在联络记录/工单内容/处理结果中，存在信息记录不准确或未记录的情况，且可能会影响后续客户问题的处理\n",
      "单句评论": "-",
      "日期": "2026-06-02",
      "差错类型": "关键信息记录错误",
      "差错描述": "有处理中贷后二线工单，坐席未备注",
      "判罚内容": "关键信息记录错误-客服在联络记录/工单内容/处理结果中，存在信息记录不准确或未记录的情况，且可能会影响后续客户问题的处理"
    },
    {
      "姓名": "何海艳",
      "组别": "热线三组",
      "质检评分": 80,
      "最近复检时间": "2026-06-02",
      "场景": "催收投诉安抚",
      "整单评论": "[2026-06-02 14:19:43]潘小佩:【质检差错】1、不要联系紧急联系人，未点借款人诉求停催联系人标签；2、咨询账单情况，小结单未记录；3、客户咨询总欠款金额，坐席沟通只告知客户8笔待还，实际客户还有逾期账单， 总需要还款笔数是11笔，坐席解答不完整，信息解读偏差\n【质检判罚】1、标签选择错误-客服未按客户问题场景、沟通情况、业务信息等选择正确的标签；2、非关键信息记录错误-主要指信息记录不准确或未记录的情况，但无需后续处理或不影响后续处理；3、服务技巧及礼仪欠佳-服务技巧不足：未掌握倾听、引导、确认等沟通技巧，导致客户需求传递不畅，或信息解读偏差，引起客户反感、增加沟通成本\n\n",
      "单句评论": "[2026-06-02 14:20:43]潘小佩:降频，不要联系预留联系人\n[2026-06-02 14:21:50]潘小佩:待还订单8笔",
      "日期": "2026-06-02",
      "差错类型": "标签选择错误",
      "差错描述": "1、不要联系紧急联系人，未点借款人诉求停催联系人标签；2、咨询账单情况，小结单未记录；3、客户咨询总欠款金额，坐席沟通只告知客户8笔待还，实际客户还有逾期账单， 总需要还款笔数是11笔，坐席解答不完整，信息解读偏差",
      "判罚内容": "1、标签选择错误-客服未按客户问题场景、沟通情况、业务信息等选择正确的标签；2、非关键信息记录错误-主要指信息记录不准确或未记录的情况，但无需后续处理或不影响后续处理；3、服务技巧及礼仪欠佳-服务技巧不足：未掌握倾听、引导、确认等沟通技巧，导致客户需求传递不畅，或信息解读偏差，引起客户反感、增加沟通成本"
    },
    {
      "姓名": "周培",
      "组别": "热线七组",
      "质检评分": 80,
      "最近复检时间": "2026-06-02",
      "场景": "超级会员取消",
      "整单评论": "[2026-06-02 14:50:59]刘倩:【质检判罚】客户表示今天扣款199，咨询为什么扣款199，客服告知今天早上十点去操作创建的会员，客户表示自己未开通会员，客服解释可能是误操作，解答有误，2026-06-02创建的会员是因为客户在2025-12-05开通会员会员季卡，开通时有点选自动续费，今天扣款是权益卡到期续费扣款。\n【质检判罚】解答错误：客户进线反馈的问题，客服错误处理或提供不准确的解决方案，导致未解决或未覆盖客户的问题；或未按照SOP准流程执行，处理不全/错误，",
      "单句评论": "-",
      "日期": "2026-06-02",
      "差错类型": "解答错误",
      "差错描述": "-",
      "判罚内容": "客户表示今天扣款199，咨询为什么扣款199，客服告知今天早上十点去操作创建的会员，客户表示自己未开通会员，客服解释可能是误操作，解答有误，2026-06-02创建的会员是因为客户在2025-12-05开通会员会员季卡，开通时有点选自动续费，今天扣款是权益卡到期续费扣款。\n【质检判罚】解答错误：客户进线反馈的问题，客服错误处理或提供不准确的解决方案，导致未解决或未覆盖客户的问题；或未按照SOP准流程执行，处理不全/错误，"
    },
    {
      "姓名": "张思婕",
      "组别": "热线八组",
      "质检评分": 75,
      "最近复检时间": "2026-06-02",
      "场景": "提前还款或结清咨询",
      "整单评论": "[2026-06-02 14:18:11]刘倩:【质检判罚】1、客户要求提前还2026-06-14账单，最后一期，还款日前还款：支持，客服告知不支持。2、沟通中客户未提及扬言投诉敏感词，小结单内也未备注，小结单误点选扬言投诉标签。\n【质检判罚】1、解答错误：客户进线反馈的问题，客服错误处理或提供不准确的解决方案，导致未解决或未覆盖客户的问题；或未按照SOP准流程执行，处理不全/错误。2、标签选择错误-客服未按客户问题场景、沟通情况、业务信息等选择正确的标签\n",
      "单句评论": "[2026-06-02 14:19:02]刘倩:告知不支持提前结清，只能6.14号还款日当天还款",
      "日期": "2026-06-02",
      "差错类型": "解答错误",
      "差错描述": "[2026-06-02 14:19:02]刘倩:告知不支持提前结清，只能6.14号还款日当天还款",
      "判罚内容": "1、客户要求提前还2026-06-14账单，最后一期，还款日前还款：支持，客服告知不支持。2、沟通中客户未提及扬言投诉敏感词，小结单内也未备注，小结单误点选扬言投诉标签。\n【质检判罚】1、解答错误：客户进线反馈的问题，客服错误处理或提供不准确的解决方案，导致未解决或未覆盖客户的问题；或未按照SOP准流程执行，处理不全/错误。2、标签选择错误-客服未按客户问题场景、沟通情况、业务信息等选择正确的标签"
    },
    {
      "姓名": "黄晓纯",
      "组别": "热线四组",
      "质检评分": 65,
      "最近复检时间": "2026-06-02",
      "场景": "协商还款",
      "整单评论": "[2026-06-02 17:43:03]段林涛:【质检差错】1、客户进线查询逾期账单，核身中提供银行卡后四位错误，坐席未追问直接跳过引导提供最高学历；2、客户逾期场景下有明确说联系资金方可以吗，坐席扬言投诉未点选，3、小结单内未备注联系资金方；\n【质检判罚】1、应核未核：应核身场景客服未核身直接办理业务或解答用户问题；2、标签选择错误：客服未按客户问题场景、沟通情况、业务信息等选择正确的标签，包括但不限于：服务标签、黑产标记、服务来源、资金方、紧急程度等各类标签，错误类型包括漏选、错选、多选等；3、关键信息记录错误：客服在联络记录/工单内容/处理结果中，存在信息记录不准确的情况，且可能会影响后续客户问题的处理，包括但不限于：回访电话、回访时间、客户问题、客户诉求等核心信息",
      "单句评论": "[2026-06-02 17:38:10]段林涛:1",
      "日期": "2026-06-02",
      "差错类型": "应核未核",
      "差错描述": "1、客户进线查询逾期账单，核身中提供银行卡后四位错误，坐席未追问直接跳过引导提供最高学历；2、客户逾期场景下有明确说联系资金方可以吗，坐席扬言投诉未点选，3、小结单内未备注联系资金方；",
      "判罚内容": "1、应核未核：应核身场景客服未核身直接办理业务或解答用户问题；2、标签选择错误：客服未按客户问题场景、沟通情况、业务信息等选择正确的标签，包括但不限于：服务标签、黑产标记、服务来源、资金方、紧急程度等各类标签，错误类型包括漏选、错选、多选等；3、关键信息记录错误：客服在联络记录/工单内容/处理结果中，存在信息记录不准确的情况，且可能会影响后续客户问题的处理，包括但不限于：回访电话、回访时间、客户问题、客户诉求等核心信息"
    },
    {
      "姓名": "王嘉乐",
      "组别": "热线五组",
      "质检评分": 80,
      "最近复检时间": "2026-06-02",
      "场景": "结清账单费率不满",
      "整单评论": "[2026-06-02 13:52:29]刘倩:【质检判罚】客户表示之前结清系统多扣款400，咨询退费处理进度，客服未咨询查看历史记录，盲目告知客户是6.1号申请，处理时效3-7个工作日。\n【质检判罚】未查看历史记录回复错误：客户历史已进线反馈问题，且有处理进展或结果，客服未查看历史进线记录、工单处理进展、工单处理结果，重复询问或提供错误方案",
      "单句评论": "-",
      "日期": "2026-06-02",
      "差错类型": "未查看历史记录回复错误",
      "差错描述": "-",
      "判罚内容": "客户表示之前结清系统多扣款400，咨询退费处理进度，客服未咨询查看历史记录，盲目告知客户是6.1号申请，处理时效3-7个工作日。\n【质检判罚】未查看历史记录回复错误：客户历史已进线反馈问题，且有处理进展或结果，客服未查看历史进线记录、工单处理进展、工单处理结果，重复询问或提供错误方案"
    },
    {
      "姓名": "李德田",
      "组别": "热线六组",
      "质检评分": 75,
      "最近复检时间": "2026-06-02",
      "场景": "账单查询",
      "整单评论": "[2026-06-02 13:51:01]潘小佩:【质检差错】1、3s内未完成开头语表述；2、沟通客户提供的号码是15950973796，坐席小结单错误备注为15950973739，记录有误\n【质检判罚】1、首触不规范-时效规则：热线：3s内完成开头语表述；2、关键信息记录错误-客服在联络记录/工单内容/处理结果中，存在信息记录不准确或未记录的情况，且可能会影响后续客户问题的处理\n\n",
      "单句评论": "[2026-06-02 13:51:21]潘小佩:15950973796",
      "日期": "2026-06-02",
      "差错类型": "首触不规范",
      "差错描述": "1、3s内未完成开头语表述；2、沟通客户提供的号码是15950973796，坐席小结单错误备注为15950973739，记录有误",
      "判罚内容": "1、首触不规范-时效规则：热线：3s内完成开头语表述；2、关键信息记录错误-客服在联络记录/工单内容/处理结果中，存在信息记录不准确或未记录的情况，且可能会影响后续客户问题的处理"
    },
    {
      "姓名": "何海艳",
      "组别": "热线三组",
      "质检评分": 80,
      "最近复检时间": "2026-06-02",
      "场景": "催收投诉安抚",
      "整单评论": "[2026-06-02 17:20:22]段林涛:【质检差错】客户进线咨询延期停催诉求，未抱怨催收问题，坐席应选“贷后流程-逾期延期还款”，坐席错选“贷后流程-投诉催收安抚”\n【质检判罚】问题分类选择错误：客服未按客户问题场景选择合适准确的小结单分类或工单分类。若智能落单推荐的小结单或工单分类不准确，需手动选择符合客户问题场景的分类，直接选择推荐分类需扣罚",
      "单句评论": "-",
      "日期": "2026-06-02",
      "差错类型": "问题分类选择错误",
      "差错描述": "客户进线咨询延期停催诉求，未抱怨催收问题，坐席应选“贷后流程-逾期延期还款”，坐席错选“贷后流程-投诉催收安抚”",
      "判罚内容": "问题分类选择错误：客服未按客户问题场景选择合适准确的小结单分类或工单分类。若智能落单推荐的小结单或工单分类不准确，需手动选择符合客户问题场景的分类，直接选择推荐分类需扣罚"
    },
    {
      "姓名": "仝圆圆",
      "组别": "热线六组",
      "质检评分": 80,
      "最近复检时间": "2026-06-03",
      "场景": "结清账单费率不满",
      "整单评论": "[2026-06-03 15:11:00]吴敌:【质检差错】客户要查询账单放款时间，并表示息费问题已达成一致，仅要求查询放款时间，三级分类应选择账单查询；\n【质检判罚】问题分类选择错误；\n",
      "单句评论": "-",
      "日期": "2026-06-03",
      "差错类型": "问题分类选择错误",
      "差错描述": "客户要查询账单放款时间，并表示息费问题已达成一致，仅要求查询放款时间，三级分类应选择账单查询；",
      "判罚内容": "问题分类选择错误；"
    },
    {
      "姓名": "吕星镇",
      "组别": "热线七组",
      "质检评分": 80,
      "最近复检时间": "2026-06-03",
      "场景": "降费卡取消",
      "整单评论": "[2026-06-03 09:38:51]王明卫:【质检差错】客户对5月20号开通的先享后付降费卡不满需取消，坐席告知关闭，核实未操作减免取消。\n【质检判罚】权益卡应退减未退减-承诺退减未退减：符合退减场景下，客服承诺客户退减权益卡，但实际未操作",
      "单句评论": "-",
      "日期": "2026-06-03",
      "差错类型": "权益卡应退减未退减",
      "差错描述": "客户对5月20号开通的先享后付降费卡不满需取消，坐席告知关闭，核实未操作减免取消。",
      "判罚内容": "权益卡应退减未退减-承诺退减未退减：符合退减场景下，客服承诺客户退减权益卡，但实际未操作"
    },
    {
      "姓名": "赵晓莹",
      "组别": "热线五组",
      "质检评分": 80,
      "最近复检时间": "2026-06-03",
      "场景": "超级会员取消",
      "整单评论": "[2026-06-03 13:56:29]潘小佩:【质检差错】退好借卡+惠享服务，小结单应为好借卡取消/降费卡取消，坐席错选超级会员取消\n【质检判罚】问题分类选择错误-客服未按客户问题场景选择合适准确的小结单分类或工单分类\n",
      "单句评论": "-",
      "日期": "2026-06-03",
      "差错类型": "问题分类选择错误",
      "差错描述": "退好借卡+惠享服务，小结单应为好借卡取消/降费卡取消，坐席错选超级会员取消",
      "判罚内容": "问题分类选择错误-客服未按客户问题场景选择合适准确的小结单分类或工单分类"
    },
    {
      "姓名": "刘迪",
      "组别": "热线六组",
      "质检评分": 80,
      "最近复检时间": "2026-06-02",
      "场景": "降费卡取消",
      "整单评论": "[2026-06-02 14:32:44]吴敌:【质检差错】客户咨询199/15两笔扣费原因，工单备注为199.15记录未能正确表达申请退费金额；\n【质检判罚】关键信息记录错误；",
      "单句评论": "-",
      "日期": "2026-06-02",
      "差错类型": "关键信息记录错误",
      "差错描述": "客户咨询199/15两笔扣费原因，工单备注为199.15记录未能正确表达申请退费金额；",
      "判罚内容": "关键信息记录错误；"
    },
    {
      "姓名": "陈北仁",
      "组别": "热线七组",
      "质检评分": 80,
      "最近复检时间": "2026-06-02",
      "场景": "账单查询",
      "整单评论": "[2026-06-02 11:47:53]王明卫:【质检差错】客户进线不需要超级会员，需退回199扣款，核身未通过离线，小结单三级类别应选择超级会员取消，坐席错选账单查询\n【质检判罚】问题分类选择错误-问题分类选择错误：客服未按客户问题场景选择合适准确的小结单分类或工单分类",
      "单句评论": "[2026-06-02 11:44:37]王明卫:不需要199超级会员需退费",
      "日期": "2026-06-02",
      "差错类型": "问题分类选择错误",
      "差错描述": "客户进线不需要超级会员，需退回199扣款，核身未通过离线，小结单三级类别应选择超级会员取消，坐席错选账单查询",
      "判罚内容": "问题分类选择错误-问题分类选择错误：客服未按客户问题场景选择合适准确的小结单分类或工单分类"
    },
    {
      "姓名": "李德田",
      "组别": "热线六组",
      "质检评分": 80,
      "最近复检时间": "2026-06-02",
      "场景": "降费卡取消",
      "整单评论": "[2026-06-01 17:14:35]段林涛:【质检差错】客户进线取消一笔60元降费权益卡，未涉及扣款无需退费，坐席已申请减免；错误备注申请退费24小时内到账；\n【质检判罚】关键信息记录错误：客服在联络记录/工单内容/处理结果中，存在信息记录不准确的情况，且可能会影响后续客户问题的处理，包括但不限于：回访电话、回访时间、客户问题、客户诉求等核心信息",
      "单句评论": "[2026-06-01 17:13:04]段林涛:1",
      "日期": "2026-06-02",
      "差错类型": "关键信息记录错误",
      "差错描述": "客户进线取消一笔60元降费权益卡，未涉及扣款无需退费，坐席已申请减免；错误备注申请退费24小时内到账；",
      "判罚内容": "关键信息记录错误：客服在联络记录/工单内容/处理结果中，存在信息记录不准确的情况，且可能会影响后续客户问题的处理，包括但不限于：回访电话、回访时间、客户问题、客户诉求等核心信息"
    },
    {
      "姓名": "张思婕",
      "组别": "热线八组",
      "质检评分": 75,
      "最近复检时间": "2026-06-01",
      "场景": "未逾期协商还款",
      "整单评论": "[2026-06-01 18:21:46]段林涛:【质检差错】客户进线未逾期协商还款，1、客户提及银监会，坐席未在小结单内备注；2、服务标签未点选；\n【质检判罚】1、关键信息记录错误：客服在联络记录/工单内容/处理结果中，存在信息记录不准确的情况，且可能会影响后续客户问题的处理，包括但不限于：回访电话、回访时间、客户问题、客户诉求等核心信息；2、标签选择错误：客服未按客户问题场景、沟通情况、业务信息等选择正确的标签，包括但不限于：服务标签、黑产标记、服务来源、资金方、紧急程度等各类标签，错误类型包括漏选、错选、多选等",
      "单句评论": "[2026-06-01 18:18:32]段林涛:1",
      "日期": "2026-06-01",
      "差错类型": "关键信息记录错误",
      "差错描述": "客户进线未逾期协商还款，1、客户提及银监会，坐席未在小结单内备注；2、服务标签未点选；",
      "判罚内容": "1、关键信息记录错误：客服在联络记录/工单内容/处理结果中，存在信息记录不准确的情况，且可能会影响后续客户问题的处理，包括但不限于：回访电话、回访时间、客户问题、客户诉求等核心信息；2、标签选择错误：客服未按客户问题场景、沟通情况、业务信息等选择正确的标签，包括但不限于：服务标签、黑产标记、服务来源、资金方、紧急程度等各类标签，错误类型包括漏选、错选、多选等"
    },
    {
      "姓名": "杜娇",
      "组别": "热线七组",
      "质检评分": 80,
      "最近复检时间": "2026-06-03",
      "场景": "超级会员取消",
      "整单评论": "[2026-06-03 12:16:21]潘小佩:【质检差错】退会员，坐席告知原路退还到农业银行卡，实际会员扣费卡是中国建设银行8108，坐席操作退的卡也是8108，坐席返回客户信息有误\n【质检判罚】解答错误-客户进线反馈的问题，客服错误处理或提供不准确的解决方案，导致未解决或未覆盖客户的问题；或未按照SOP准流程执行，处理不全/错误，包括但不限于：产品规则解答错误、政策条款解答错误、操作指引介绍错误及信息数据回复错误等\n\n",
      "单句评论": "[2026-06-03 12:14:38]潘小佩:退农业银行",
      "日期": "2026-06-03",
      "差错类型": "解答错误",
      "差错描述": "退会员，坐席告知原路退还到农业银行卡，实际会员扣费卡是中国建设银行8108，坐席操作退的卡也是8108，坐席返回客户信息有误",
      "判罚内容": "解答错误-客户进线反馈的问题，客服错误处理或提供不准确的解决方案，导致未解决或未覆盖客户的问题；或未按照SOP准流程执行，处理不全/错误，包括但不限于：产品规则解答错误、政策条款解答错误、操作指引介绍错误及信息数据回复错误等"
    },
    {
      "姓名": "何海艳",
      "组别": "热线三组",
      "质检评分": 80,
      "最近复检时间": "2026-06-02",
      "场景": "结清证明申请",
      "整单评论": "[2026-06-02 15:02:47]王明卫:【质检差错】客户因注册号码注销需开具结清证明，坐席核实后告知客户登录APP-选择其他方式登录-原手机不再使用-现在使用的手机号登录-我的-开具结清证明，解答错误，此场景可引导客户修改注册号码后登录APP开具结清证明或提供注册号码注销证明，核身通过后，坐席协助开具结清证明\n【质检判罚】解答错误-解答错误：客户进线反馈的问题，客服错误处理或提供不准确的解决方案，导致未解决或未覆盖客户的问题；或未按照SOP准流程执行，处理不全/错误",
      "单句评论": "[2026-06-02 14:58:01]王明卫:1",
      "日期": "2026-06-02",
      "差错类型": "解答错误",
      "差错描述": "客户因注册号码注销需开具结清证明，坐席核实后告知客户登录APP-选择其他方式登录-原手机不再使用-现在使用的手机号登录-我的-开具结清证明，解答错误，此场景可引导客户修改注册号码后登录APP开具结清证明或提供注册号码注销证明，核身通过后，坐席协助开具结清证明",
      "判罚内容": "解答错误-解答错误：客户进线反馈的问题，客服错误处理或提供不准确的解决方案，导致未解决或未覆盖客户的问题；或未按照SOP准流程执行，处理不全/错误"
    },
    {
      "姓名": "周培",
      "组别": "热线七组",
      "质检评分": 80,
      "最近复检时间": "2026-06-01",
      "场景": "未结清账单费率不满",
      "整单评论": "[2026-06-01 16:09:11]潘小佩:【质检差错】账单逾期申请减免，小结单应为协商还款，坐席错选未结清账单费率不满（ 5.25号 10:22岗中培训群已同步小结单点选变更）\n【质检判罚】问题分类选择错误-客服未按客户问题场景选择合适准确的小结单分类或工单分类\n",
      "单句评论": "-",
      "日期": "2026-06-01",
      "差错类型": "问题分类选择错误",
      "差错描述": "账单逾期申请减免，小结单应为协商还款，坐席错选未结清账单费率不满（ 5.25号 10:22岗中培训群已同步小结单点选变更）",
      "判罚内容": "问题分类选择错误-客服未按客户问题场景选择合适准确的小结单分类或工单分类"
    },
    {
      "姓名": "李德田",
      "组别": "热线六组",
      "质检评分": 80,
      "最近复检时间": "2026-06-01",
      "场景": "征信上报规则",
      "整单评论": "[2026-06-01 16:40:07]刘倩:【质检差错】客户咨询授信额度，无融担账户，小结单应该选择：征信相关问题-征信问题咨询-资金方-征信上报规则。 【质检判罚】问题分类选择错误-客服未按客户问题场景选择合适准确的小结单分类或工单分类。",
      "单句评论": "-",
      "日期": "2026-06-01",
      "差错类型": "问题分类选择错误",
      "差错描述": "客户咨询授信额度，无融担账户，小结单应该选择：征信相关问题-征信问题咨询-资金方-征信上报规则。",
      "判罚内容": "问题分类选择错误-客服未按客户问题场景选择合适准确的小结单分类或工单分类。"
    },
    {
      "姓名": "王嘉乐",
      "组别": "热线五组",
      "质检评分": 80,
      "最近复检时间": "2026-06-01",
      "场景": "调取合同申请",
      "整单评论": "[2026-06-01 16:42:27]刘倩:【质检差错】客户因提前还款，要求查看合同，有处理中的还款费率工单，客服未追加备注。\n【质检判罚】关键信息记录错误：客服在联络记录/工单内容/处理结果中，存在信息记录不准确或未记录的情况，且可能会影响后续客户问题的处理。",
      "单句评论": "-",
      "日期": "2026-06-01",
      "差错类型": "关键信息记录错误",
      "差错描述": "客户因提前还款，要求查看合同，有处理中的还款费率工单，客服未追加备注。",
      "判罚内容": "关键信息记录错误：客服在联络记录/工单内容/处理结果中，存在信息记录不准确或未记录的情况，且可能会影响后续客户问题的处理。"
    },
    {
      "姓名": "周培",
      "组别": "热线七组",
      "质检评分": 70,
      "最近复检时间": "2026-06-01",
      "场景": "协商还款",
      "整单评论": "[2026-06-01 18:16:56]王明卫:【质检差错】1、客户进线需协商还款，安抚未认可，客户离线，需升级处理坐席未建单升级，应升未升；2、核身流程中，客户收不到验证码，坐席直接换问题核验，未按照业务流程处理。\n【质检判罚】1、应升未升/应转未转-应升未升：按业务 SOP 应升级场景，客服未创建升级工单；2、应核未核-应核未核：应核身场景客服未核身直接办理业务或解答用户问题",
      "单句评论": "[2026-06-01 17:15:44]王明卫:客户收不到验证未引导提供凭证直接换问题",
      "日期": "2026-06-01",
      "差错类型": "应升未升/应转未转",
      "差错描述": "1、客户进线需协商还款，安抚未认可，客户离线，需升级处理坐席未建单升级，应升未升；2、核身流程中，客户收不到验证码，坐席直接换问题核验，未按照业务流程处理。",
      "判罚内容": "1、应升未升/应转未转-应升未升：按业务 SOP 应升级场景，客服未创建升级工单；2、应核未核-应核未核：应核身场景客服未核身直接办理业务或解答用户问题"
    },
    {
      "姓名": "张思婕",
      "组别": "热线八组",
      "质检评分": 80,
      "最近复检时间": "2026-06-01",
      "场景": "账单查询",
      "整单评论": "[2026-06-01 17:20:07]段林涛:【质检差错】客户进行咨询会员、查询273077922账单，坐席错误告知结清金额为1041.5；已结清的金额不可对客告知；\n【质检判罚】解答错误：客户进线反馈的问题，客服错误处理或提供不准确的解决方案，导致未解决或未覆盖客户的问题；或未按照SOP准流程执行，处理不全/错误，包括但不限于：产品规则解答错误、政策条款解答错误、操作指引介绍错误及信息数据回复错误等\n",
      "单句评论": "[2026-06-01 17:17:42]段林涛:1\n[2026-06-01 17:17:45]段林涛:1",
      "日期": "2026-06-01",
      "差错类型": "解答错误",
      "差错描述": "客户进行咨询会员、查询273077922账单，坐席错误告知结清金额为1041.5；已结清的金额不可对客告知；",
      "判罚内容": "解答错误：客户进线反馈的问题，客服错误处理或提供不准确的解决方案，导致未解决或未覆盖客户的问题；或未按照SOP准流程执行，处理不全/错误，包括但不限于：产品规则解答错误、政策条款解答错误、操作指引介绍错误及信息数据回复错误等"
    },
    {
      "姓名": "周培",
      "组别": "热线七组",
      "质检评分": 80,
      "最近复检时间": "2026-06-01",
      "场景": "未结清账单费率不满",
      "整单评论": "[2026-06-01 17:13:58]王明卫:【质检差错】协助操作减免逾期费用，小结单三级类别应选择协商还款，坐席错选未结清账单费率不满\n【质检判罚】问题分类选择错误-问题分类选择错误：客服未按客户问题场景选择合适准确的小结单分类或工单分类",
      "单句评论": "-",
      "日期": "2026-06-01",
      "差错类型": "问题分类选择错误",
      "差错描述": "协助操作减免逾期费用，小结单三级类别应选择协商还款，坐席错选未结清账单费率不满",
      "判罚内容": "问题分类选择错误-问题分类选择错误：客服未按客户问题场景选择合适准确的小结单分类或工单分类"
    },
    {
      "姓名": "陈北仁",
      "组别": "热线七组",
      "质检评分": 80,
      "最近复检时间": "2026-06-03",
      "场景": "营销活动咨询",
      "整单评论": "[2026-06-03 11:52:59]段林涛:【质检差错】客户进线咨询天创信用扣款49.9明确说要退回来，坐席引导联系，错选“增值服务-营销活动咨询”，客户明确说到退费需点选“增值服务-营销活动退款”\n【质检判罚】问题分类选择错误：客服未按客户问题场景选择合适准确的小结单分类或工单分类。若智能落单推荐的小结单或工单分类不准确，需手动选择符合客户问题场景的分类，直接选择推荐分类需扣罚",
      "单句评论": "[2026-06-03 11:50:32]段林涛:1",
      "日期": "2026-06-03",
      "差错类型": "问题分类选择错误",
      "差错描述": "客户进线咨询天创信用扣款49.9明确说要退回来，坐席引导联系，错选“增值服务-营销活动咨询”，客户明确说到退费需点选“增值服务-营销活动退款”",
      "判罚内容": "问题分类选择错误：客服未按客户问题场景选择合适准确的小结单分类或工单分类。若智能落单推荐的小结单或工单分类不准确，需手动选择符合客户问题场景的分类，直接选择推荐分类需扣罚"
    },
    {
      "姓名": "穆琪",
      "组别": "热线三组",
      "质检评分": 70,
      "最近复检时间": "2026-06-01",
      "场景": "协商还款",
      "整单评论": "[2026-06-01 17:11:09]王明卫:【质检差错】1、客户进线申请延期停催业务，会话中坐席言贷后和客服不是一个平台，解答错误；2、核实问题未使用静音键进行等待；3、客户有停催联系人诉求，未点选借款人诉求停催联系人标签\n【质检判罚】1、解答错误-解答错误：客户进线反馈的问题，客服错误处理或提供不准确的解决方案，导致未解决或未覆盖客户的问题；或未按照SOP准流程执行，处理不全/错误；2、等待不规范-.等待操作不规范：未使用静音键进行等待；3、标签选择错误-标签选择错误：客服未按客户问题场景、沟通情况、业务信息等选择正确的标签",
      "单句评论": "[2026-06-01 17:05:43]王明卫:未正确使用静音键\n[2026-06-01 17:06:16]王明卫:停催联系人诉求",
      "日期": "2026-06-01",
      "差错类型": "解答错误",
      "差错描述": "1、客户进线申请延期停催业务，会话中坐席言贷后和客服不是一个平台，解答错误；2、核实问题未使用静音键进行等待；3、客户有停催联系人诉求，未点选借款人诉求停催联系人标签",
      "判罚内容": "1、解答错误-解答错误：客户进线反馈的问题，客服错误处理或提供不准确的解决方案，导致未解决或未覆盖客户的问题；或未按照SOP准流程执行，处理不全/错误；2、等待不规范-.等待操作不规范：未使用静音键进行等待；3、标签选择错误-标签选择错误：客服未按客户问题场景、沟通情况、业务信息等选择正确的标签"
    },
    {
      "姓名": "李旻宁",
      "组别": "热线八组",
      "质检评分": 80,
      "最近复检时间": "2026-06-02",
      "场景": "降费卡取消",
      "整单评论": "[2026-06-02 15:28:32]吴敌:【质检差错】权益卡可查询范围要求关闭自动续费，客服未按流程操作，要求客户提供扣费时间凭证；\n【质检判罚】解答错误；",
      "单句评论": "-",
      "日期": "2026-06-02",
      "差错类型": "解答错误",
      "差错描述": "权益卡可查询范围要求关闭自动续费，客服未按流程操作，要求客户提供扣费时间凭证；",
      "判罚内容": "解答错误；"
    },
    {
      "姓名": "李德田",
      "组别": "热线六组",
      "质检评分": 80,
      "最近复检时间": "2026-06-01",
      "场景": "超级会员取消",
      "整单评论": "[2026-06-01 16:53:22]王明卫:【质检差错】客户申请会员退费，坐席告知原路退回，核实退费未操作，承诺退减未退减\n【质检判罚】权益卡应退减未退减-承诺退减未退减：符合退减场景下，客服承诺客户退减权益卡，但实际未操作",
      "单句评论": "-",
      "日期": "2026-06-01",
      "差错类型": "权益卡应退减未退减",
      "差错描述": "客户申请会员退费，坐席告知原路退回，核实退费未操作，承诺退减未退减",
      "判罚内容": "权益卡应退减未退减-承诺退减未退减：符合退减场景下，客服承诺客户退减权益卡，但实际未操作"
    },
    {
      "姓名": "穆琪",
      "组别": "热线三组",
      "质检评分": 80,
      "最近复检时间": "2026-06-01",
      "场景": "协商还款",
      "整单评论": "[2026-06-01 16:16:52]潘小佩:【质检差错】反馈暂时无法还款，沟通坐席告知客户账单待还款，没逾期不会有催收人员联系，实际客户\n2026-05-28，2026-05-30，2026-05-31的账单已经逾期，坐席返回客户信息有误\n【质检判罚】解答错误-客户进线反馈的问题，客服错误处理或提供不准确的解决方案，导致未解决或未覆盖客户的问题；或未按照SOP准流程执行，处理不全/错误，包括但不限于：产品规则解答错误、政策条款解答错误、操作指引介绍错误及信息数据回复错误等\n",
      "单句评论": "[2026-06-01 16:16:06]潘小佩:账单待还款，不会有催收人员联系，实际好几笔账单已经逾期",
      "日期": "2026-06-01",
      "差错类型": "解答错误",
      "差错描述": "反馈暂时无法还款，沟通坐席告知客户账单待还款，没逾期不会有催收人员联系，实际客户\n2026-05-28，2026-05-30，2026-05-31的账单已经逾期，坐席返回客户信息有误",
      "判罚内容": "解答错误-客户进线反馈的问题，客服错误处理或提供不准确的解决方案，导致未解决或未覆盖客户的问题；或未按照SOP准流程执行，处理不全/错误，包括但不限于：产品规则解答错误、政策条款解答错误、操作指引介绍错误及信息数据回复错误等"
    },
    {
      "姓名": "杨元婷",
      "组别": "热线一组",
      "质检评分": 80,
      "最近复检时间": "2026-06-03",
      "场景": "超级会员取消",
      "整单评论": "[2026-06-03 11:11:09]潘小佩:【质检差错】会员退款，坐席询问退费卡，客户表示退到扣费卡农业银行，坐席告知客户是中国银行扣款的，返回客户信息有误，客户199扣费成功的卡是中国农业银行*7415，并非中国银行(4970)\n【质检判罚】解答错误-客户进线反馈的问题，客服错误处理或提供不准确的解决方案，导致未解决或未覆盖客户的问题；或未按照SOP准流程执行，处理不全/错误，包括但不限于：产品规则解答错误、政策条款解答错误、操作指引介绍错误及信息数据回复错误等\n",
      "单句评论": "-",
      "日期": "2026-06-03",
      "差错类型": "解答错误",
      "差错描述": "会员退款，坐席询问退费卡，客户表示退到扣费卡农业银行，坐席告知客户是中国银行扣款的，返回客户信息有误，客户199扣费成功的卡是中国农业银行*7415，并非中国银行(4970)",
      "判罚内容": "解答错误-客户进线反馈的问题，客服错误处理或提供不准确的解决方案，导致未解决或未覆盖客户的问题；或未按照SOP准流程执行，处理不全/错误，包括但不限于：产品规则解答错误、政策条款解答错误、操作指引介绍错误及信息数据回复错误等"
    },
    {
      "姓名": "崔珂",
      "组别": "热线三组",
      "质检评分": 80,
      "最近复检时间": "2026-06-03",
      "场景": "未结清账单费率不满",
      "整单评论": "[2026-06-03 13:28:19]杨姿娇:【质检差错】坐席转接告知常规转接组：客户无退息记录和注销记录，实际客户2026/2/10新客退过息，错误转接\n【质检判罚】不应升但升/不应转但转-不应转但转：按业务 SOP 应自闭环场景，或不满足转接条件，客服错误转接",
      "单句评论": "[2026-06-03 13:26:20]杨姿娇:坐席告知无退息记录，注销记录，实际客户2026/2/10新客退过息",
      "日期": "2026-06-03",
      "差错类型": "不应升但升/不应转但转",
      "差错描述": "坐席转接告知常规转接组：客户无退息记录和注销记录，实际客户2026/2/10新客退过息，错误转接",
      "判罚内容": "不应升但升/不应转但转-不应转但转：按业务 SOP 应自闭环场景，或不满足转接条件，客服错误转接"
    },
    {
      "姓名": "仝圆圆",
      "组别": "热线六组",
      "质检评分": 80,
      "最近复检时间": "2026-06-02",
      "场景": "开具发票申请",
      "整单评论": "[2026-06-02 10:34:14]段林涛:【质检差错】客户进线咨询发票问题，询问是否有解压码，坐席未进一步确认错误告知为身份证号码；结清证明有解压码；发票无需解压码；\n【质检判罚】解答错误：客户进线反馈的问题，客服错误处理或提供不准确的解决方案，导致未解决或未覆盖客户的问题；或未按照SOP准流程执行，处理不全/错误，包括但不限于：产品规则解答错误、政策条款解答错误、操作指引介绍错误及信息数据回复错误等",
      "单句评论": "[2026-06-02 10:30:33]段林涛:诉求模糊，坐席未探寻",
      "日期": "2026-06-02",
      "差错类型": "解答错误",
      "差错描述": "客户进线咨询发票问题，询问是否有解压码，坐席未进一步确认错误告知为身份证号码；结清证明有解压码；发票无需解压码；",
      "判罚内容": "解答错误：客户进线反馈的问题，客服错误处理或提供不准确的解决方案，导致未解决或未覆盖客户的问题；或未按照SOP准流程执行，处理不全/错误，包括但不限于：产品规则解答错误、政策条款解答错误、操作指引介绍错误及信息数据回复错误等"
    },
    {
      "姓名": "蒲园园",
      "组别": "热线三组",
      "质检评分": 80,
      "最近复检时间": "2026-06-02",
      "场景": "账单查询",
      "整单评论": "[2026-06-02 10:57:04]段林涛:【质检差错】客户进线协商减免罚息和利息，客户无查看账单诉求，坐席错选还款流程-账单查询；\n【质检判罚】问题分类选择错误：客服未按客户问题场景选择合适准确的小结单分类或工单分类。若智能落单推荐的小结单或工单分类不准确，需手动选择符合客户问题场景的分类，直接选择推荐分类需扣罚",
      "单句评论": "[2026-06-02 10:55:28]段林涛:1",
      "日期": "2026-06-02",
      "差错类型": "问题分类选择错误",
      "差错描述": "客户进线协商减免罚息和利息，客户无查看账单诉求，坐席错选还款流程-账单查询；",
      "判罚内容": "问题分类选择错误：客服未按客户问题场景选择合适准确的小结单分类或工单分类。若智能落单推荐的小结单或工单分类不准确，需手动选择符合客户问题场景的分类，直接选择推荐分类需扣罚"
    },
    {
      "姓名": "樊凯飞",
      "组别": "热线六组",
      "质检评分": 80,
      "最近复检时间": "2026-06-02",
      "场景": "未结清账单费率不满",
      "整单评论": "[2026-06-02 15:37:53]段林涛:【质检差错】客户进线对利息担保费不认可，客户逾期状态下坐席错选“特殊业务咨询办理-未结清费率不满”，应点选“贷后流程-协商还款”\n【质检判罚】问题分类选择错误：客服未按客户问题场景选择合适准确的小结单分类或工单分类。若智能落单推荐的小结单或工单分类不准确，需手动选择符合客户问题场景的分类，直接选择推荐分类需扣罚",
      "单句评论": "-",
      "日期": "2026-06-02",
      "差错类型": "问题分类选择错误",
      "差错描述": "客户进线对利息担保费不认可，客户逾期状态下坐席错选“特殊业务咨询办理-未结清费率不满”，应点选“贷后流程-协商还款”",
      "判罚内容": "问题分类选择错误：客服未按客户问题场景选择合适准确的小结单分类或工单分类。若智能落单推荐的小结单或工单分类不准确，需手动选择符合客户问题场景的分类，直接选择推荐分类需扣罚"
    },
    {
      "姓名": "胡鑫",
      "组别": "热线三组",
      "质检评分": 80,
      "最近复检时间": "2026-06-01",
      "场景": "临时特殊队列",
      "整单评论": "[2026-06-01 15:24:46]杨姿娇:【质检差错】4月1日通知：遇到法诉用户协商还款，一二线：坐席无需谈判直接建单贷后，建单规范 贷后流程—协商还款—协商还款 （关键词 需贷后跟进）；如客户是诉前-确认与法诉的协商方案、诉中-诉前和解 结清后询问撤诉进度、诉后-法诉完成  汇款法院后询问结清进度，建单规范 贷后流程-其他-临时特殊列队-法诉用户（关键词）\n【质检判罚】问题分类选择错误：客服未按客户问题场景选择合适准确的小结单分类或工单分类",
      "单句评论": "-",
      "日期": "2026-06-01",
      "差错类型": "问题分类选择错误",
      "差错描述": "4月1日通知：遇到法诉用户协商还款，一二线：坐席无需谈判直接建单贷后，建单规范 贷后流程—协商还款—协商还款 （关键词 需贷后跟进）；如客户是诉前-确认与法诉的协商方案、诉中-诉前和解 结清后询问撤诉进度、诉后-法诉完成  汇款法院后询问结清进度，建单规范 贷后流程-其他-临时特殊列队-法诉用户（关键词）",
      "判罚内容": "问题分类选择错误：客服未按客户问题场景选择合适准确的小结单分类或工单分类"
    },
    {
      "姓名": "王朝",
      "组别": "热线六组",
      "质检评分": 80,
      "最近复检时间": "2026-06-02",
      "场景": "账单查询",
      "整单评论": "[2026-06-02 14:28:49]段林涛:【质检差错】客户进线咨询扣款记录4月23日明确说到扣款69元，坐席错记为6元；\n【质检判罚】关键信息记录错误：客服在联络记录/工单内容/处理结果中，存在信息记录不准确的情况，且可能会影响后续客户问题的处理，包括但不限于：回访电话、回访时间、客户问题、客户诉求等核心信息",
      "单句评论": "[2026-06-02 14:27:09]段林涛:1",
      "日期": "2026-06-02",
      "差错类型": "关键信息记录错误",
      "差错描述": "客户进线咨询扣款记录4月23日明确说到扣款69元，坐席错记为6元；",
      "判罚内容": "关键信息记录错误：客服在联络记录/工单内容/处理结果中，存在信息记录不准确的情况，且可能会影响后续客户问题的处理，包括但不限于：回访电话、回访时间、客户问题、客户诉求等核心信息"
    },
    {
      "姓名": "卜浩",
      "组别": "热线五组",
      "质检评分": 0,
      "最近复检时间": "2026-06-02",
      "场景": "好借卡取消",
      "整单评论": "[2026-06-02 14:05:19]段林涛:【质检差错】客户进线咨询权益卡自己未购买被扣款要求退费，沟通中借款人爱人插话，坐席提醒本人讲话或授权家人，要么就一个人讲话就行，引发客户不满，且沟通中坐席过度使用文明用语话术（有挂机倾向）激怒客户，与客户产生争执，全程坐席态度强势且未对客户情绪进行安抚引发客户不满，导致客户问题解决完后，扬言银监会投诉；\n【质检判罚】三级违规-言辞不当-态度强势，扣款100；情绪急躁：客户不认可处理方案时，客服沟通中表现出明显烦躁或急躁情绪，或言语上对客户的诉求、问题或意见表现出厌烦或明显的不愿意继续对话的态度",
      "单句评论": "-",
      "日期": "2026-06-02",
      "差错类型": "三级违规",
      "差错描述": "客户进线咨询权益卡自己未购买被扣款要求退费，沟通中借款人爱人插话，坐席提醒本人讲话或授权家人，要么就一个人讲话就行，引发客户不满，且沟通中坐席过度使用文明用语话术（有挂机倾向）激怒客户，与客户产生争执，全程坐席态度强势且未对客户情绪进行安抚引发客户不满，导致客户问题解决完后，扬言银监会投诉；",
      "判罚内容": "三级违规-言辞不当-态度强势，扣款100；情绪急躁：客户不认可处理方案时，客服沟通中表现出明显烦躁或急躁情绪，或言语上对客户的诉求、问题或意见表现出厌烦或明显的不愿意继续对话的态度"
    },
    {
      "姓名": "何遐威",
      "组别": "热线六组",
      "质检评分": 80,
      "最近复检时间": "2026-06-01",
      "场景": "好借卡取消",
      "整单评论": "[2026-06-01 09:44:04]王明卫:【质检差错】协助操作减免取消惠享服务权益卡，小结单三级类别应选择降费卡取消，坐席错选好借卡取消\n【质检判罚】问题分类选择错误-问题分类选择错误：客服未按客户问题场景选择合适准确的小结单分类或工单分类",
      "单句评论": "-",
      "日期": "2026-06-01",
      "差错类型": "问题分类选择错误",
      "差错描述": "协助操作减免取消惠享服务权益卡，小结单三级类别应选择降费卡取消，坐席错选好借卡取消",
      "判罚内容": "问题分类选择错误-问题分类选择错误：客服未按客户问题场景选择合适准确的小结单分类或工单分类"
    },
    {
      "姓名": "李静",
      "组别": "热线三组",
      "质检评分": 80,
      "最近复检时间": "2026-06-01",
      "场景": "结清账单费率不满",
      "整单评论": "[2026-06-01 09:37:43]王明卫:【质检差错】客户账单逾期进线需退息和协商处理逾期账单还款问题，安抚不认可升级贷后二线处理，小结单三级类别应选择协商还款，坐席错选结清账单费率不满\n【质检判罚】问题分类选择错误-问题分类选择错误：客服未按客户问题场景选择合适准确的小结单分类或工单分类",
      "单句评论": "-",
      "日期": "2026-06-01",
      "差错类型": "问题分类选择错误",
      "差错描述": "客户账单逾期进线需退息和协商处理逾期账单还款问题，安抚不认可升级贷后二线处理，小结单三级类别应选择协商还款，坐席错选结清账单费率不满",
      "判罚内容": "问题分类选择错误-问题分类选择错误：客服未按客户问题场景选择合适准确的小结单分类或工单分类"
    },
    {
      "姓名": "李彦霏",
      "组别": "热线二组",
      "质检评分": 80,
      "最近复检时间": "2026-06-01",
      "场景": "未结清账单费率不满",
      "整单评论": "[2026-06-01 09:23:50]王明卫:【质检差错】客户进线需处理账单费率问题，在线转接处理，有处理中的费率不满工单未备注\n【质检判罚】关键信息记录错误-关键信息记录错误：客服在联络记录/工单内容/处理结果中，存在信息记录不准确或未记录的情况，且可能会影响后续客户问题的处理",
      "单句评论": "-",
      "日期": "2026-06-01",
      "差错类型": "关键信息记录错误",
      "差错描述": "客户进线需处理账单费率问题，在线转接处理，有处理中的费率不满工单未备注",
      "判罚内容": "关键信息记录错误-关键信息记录错误：客服在联络记录/工单内容/处理结果中，存在信息记录不准确或未记录的情况，且可能会影响后续客户问题的处理"
    },
    {
      "姓名": "王佳睿",
      "组别": "热线六组",
      "质检评分": 80,
      "最近复检时间": "2026-06-01",
      "场景": "当期还款办理",
      "整单评论": "[2026-06-01 16:52:58]潘小佩:【质检差错】已还期数是0，不支持微信还款，坐席错误告知微信，解答有误\n【质检判罚】解答错误-客户进线反馈的问题，客服错误处理或提供不准确的解决方案，导致未解决或未覆盖客户的问题；或未按照SOP准流程执行，处理不全/错误，包括但不限于：产品规则解答错误、政策条款解答错误、操作指引介绍错误及信息数据回复错误等\n",
      "单句评论": "[2026-06-01 16:53:20]潘小佩:开通其他还款方式，微信/支付宝",
      "日期": "2026-06-01",
      "差错类型": "解答错误",
      "差错描述": "已还期数是0，不支持微信还款，坐席错误告知微信，解答有误",
      "判罚内容": "解答错误-客户进线反馈的问题，客服错误处理或提供不准确的解决方案，导致未解决或未覆盖客户的问题；或未按照SOP准流程执行，处理不全/错误，包括但不限于：产品规则解答错误、政策条款解答错误、操作指引介绍错误及信息数据回复错误等"
    },
    {
      "姓名": "席龙",
      "组别": "热线三组",
      "质检评分": 80,
      "最近复检时间": "2026-06-01",
      "场景": "催收投诉安抚",
      "整单评论": "[2026-06-01 12:58:29]潘小佩:【质检差错】反馈催收频次高，延期还款，小结单应为催收投诉安抚，坐席 错选逾期客户延期还款\n【质检判罚】问题分类选择错误-客服未按客户问题场景选择合适准确的小结单分类或工单分类\n",
      "单句评论": "-",
      "日期": "2026-06-01",
      "差错类型": "问题分类选择错误",
      "差错描述": "反馈催收频次高，延期还款，小结单应为催收投诉安抚，坐席 错选逾期客户延期还款",
      "判罚内容": "问题分类选择错误-客服未按客户问题场景选择合适准确的小结单分类或工单分类"
    },
    {
      "姓名": "柴倩茹",
      "组别": "热线八组",
      "质检评分": 80,
      "最近复检时间": "2026-06-01",
      "场景": "临时特殊队列",
      "整单评论": "[2026-06-01 17:25:30]杨姿娇:【质检差错】4月1日通知：遇到法诉用户协商还款，一二线：坐席无需谈判直接建单贷后，建单规范 贷后流程—协商还款—协商还款 （关键词 需贷后跟进）；如客户是诉前-确认与法诉的协商方案、诉中-诉前和解 结清后询问撤诉进度、诉后-法诉完成 汇款法院后询问结清进度，建单规范 贷后流程-其他-临时特殊列队-法诉用户（关键词） ；此客户沟通不涉及诉前、诉中、诉后相关，小结及工单类型点选不符合场景\n【质检判罚】问题分类选择错误：客服未按客户问题场景选择合适准确的小结单分类或工单分类",
      "单句评论": "-",
      "日期": "2026-06-01",
      "差错类型": "问题分类选择错误",
      "差错描述": "4月1日通知：遇到法诉用户协商还款，一二线：坐席无需谈判直接建单贷后，建单规范 贷后流程—协商还款—协商还款 （关键词 需贷后跟进）；如客户是诉前-确认与法诉的协商方案、诉中-诉前和解 结清后询问撤诉进度、诉后-法诉完成 汇款法院后询问结清进度，建单规范 贷后流程-其他-临时特殊列队-法诉用户（关键词） ；此客户沟通不涉及诉前、诉中、诉后相关，小结及工单类型点选不符合场景",
      "判罚内容": "问题分类选择错误：客服未按客户问题场景选择合适准确的小结单分类或工单分类"
    },
    {
      "姓名": "周培",
      "组别": "热线七组",
      "质检评分": 80,
      "最近复检时间": "2026-06-01",
      "场景": "-",
      "整单评论": "[2026-06-01 16:55:49]段林涛:【质检差错】小结单未保存，坐席未在全员群报备；\n【质检判罚】问题分类选择错误：客服未按客户问题场景选择合适准确的小结单分类或工单分类。若智能落单推荐的小结单或工单分类不准确，需手动选择符合客户问题场景的分类，直接选择推荐分类需扣罚",
      "单句评论": "-",
      "日期": "2026-06-01",
      "差错类型": "问题分类选择错误",
      "差错描述": "小结单未保存，坐席未在全员群报备；",
      "判罚内容": "问题分类选择错误：客服未按客户问题场景选择合适准确的小结单分类或工单分类。若智能落单推荐的小结单或工单分类不准确，需手动选择符合客户问题场景的分类，直接选择推荐分类需扣罚"
    },
    {
      "姓名": "王嘉乐",
      "组别": "热线五组",
      "质检评分": 80,
      "最近复检时间": "2026-06-01",
      "场景": "账单查询",
      "整单评论": "[2026-06-01 15:08:04]段林涛:【质检差错】客户进线咨询25号结清账单明确息费不满，且有处理中的费率工单，坐席未查看进线记录错误点选小结单；\n【质检判罚】问题分类选择错误：客服未按客户问题场景选择合适准确的小结单分类或工单分类。若智能落单推荐的小结单或工单分类不准确，需手动选择符合客户问题场景的分类，直接选择推荐分类需扣罚",
      "单句评论": "[2026-06-01 15:06:26]段林涛:1",
      "日期": "2026-06-01",
      "差错类型": "问题分类选择错误",
      "差错描述": "客户进线咨询25号结清账单明确息费不满，且有处理中的费率工单，坐席未查看进线记录错误点选小结单；",
      "判罚内容": "问题分类选择错误：客服未按客户问题场景选择合适准确的小结单分类或工单分类。若智能落单推荐的小结单或工单分类不准确，需手动选择符合客户问题场景的分类，直接选择推荐分类需扣罚"
    },
    {
      "姓名": "李德田",
      "组别": "热线六组",
      "质检评分": 80,
      "最近复检时间": "2026-06-01",
      "场景": "-",
      "整单评论": "[2026-06-01 11:04:29]段林涛:【质检差错】客户进线查看合同，借款完整合同啊加全部还款明细，坐席未保存小结单。全员群未报备；\n【质检判罚】问题分类选择错误：客服未按客户问题场景选择合适准确的小结单分类或工单分类。若智能落单推荐的小结单或工单分类不准确，需手动选择符合客户问题场景的分类，直接选择推荐分类需扣罚",
      "单句评论": "-",
      "日期": "2026-06-01",
      "差错类型": "问题分类选择错误",
      "差错描述": "客户进线查看合同，借款完整合同啊加全部还款明细，坐席未保存小结单。全员群未报备；",
      "判罚内容": "问题分类选择错误：客服未按客户问题场景选择合适准确的小结单分类或工单分类。若智能落单推荐的小结单或工单分类不准确，需手动选择符合客户问题场景的分类，直接选择推荐分类需扣罚"
    },
    {
      "姓名": "何海艳",
      "组别": "热线三组",
      "质检评分": 80,
      "最近复检时间": "2026-06-01",
      "场景": "超级会员咨询",
      "整单评论": "[2026-06-01 16:30:53]段林涛:【质检差错】客户进线咨询退他人权益卡，坐席引导本人进线/提供相关授权即可办理，客户认可；坐席错选超级会员咨询；\n【质检判罚】问题分类选择错误：客服未按客户问题场景选择合适准确的小结单分类或工单分类。若智能落单推荐的小结单或工单分类不准确，需手动选择符合客户问题场景的分类，直接选择推荐分类需扣罚",
      "单句评论": "[2026-06-01 16:27:42]段林涛:1",
      "日期": "2026-06-01",
      "差错类型": "问题分类选择错误",
      "差错描述": "客户进线咨询退他人权益卡，坐席引导本人进线/提供相关授权即可办理，客户认可；坐席错选超级会员咨询；",
      "判罚内容": "问题分类选择错误：客服未按客户问题场景选择合适准确的小结单分类或工单分类。若智能落单推荐的小结单或工单分类不准确，需手动选择符合客户问题场景的分类，直接选择推荐分类需扣罚"
    },
    {
      "姓名": "毛戈源",
      "组别": "热线五组",
      "质检评分": 60,
      "最近复检时间": "2026-06-03",
      "场景": "电话无声&无应答",
      "整单评论": "[2026-06-03 12:44:27]刘倩:【质检差错】1、12:14:45（00:00:08）客户要求退会员，小结单备注：客户进线未说明诉求，小结单备注与沟通情况不符。2、客户要求退会员，小结单应该选择：超级会员取消。若未听清客户 【质检判罚】1、关键信息记录错误：客服在联络记录/工单内容/处理结果中，存在信息记录不准确或未记录的情况，且可能会影响后续客户问题的处理。2、题分类选择错误-客服未按客户问题场景选择合适准确的小结单分类或工单分类。",
      "单句评论": "-",
      "日期": "2026-06-03",
      "差错类型": "关键信息记录错误",
      "差错描述": "1、12:14:45（00:00:08）客户要求退会员，小结单备注：客户进线未说明诉求，小结单备注与沟通情况不符。2、客户要求退会员，小结单应该选择：超级会员取消。若未听清客户",
      "判罚内容": "1、关键信息记录错误：客服在联络记录/工单内容/处理结果中，存在信息记录不准确或未记录的情况，且可能会影响后续客户问题的处理。2、题分类选择错误-客服未按客户问题场景选择合适准确的小结单分类或工单分类。"
    },
    {
      "姓名": "刘影",
      "组别": "热线五组",
      "质检评分": 60,
      "最近复检时间": "2026-06-02",
      "场景": "临时特殊队列",
      "整单评论": "[2026-06-02 09:35:17]杨姿娇:【质检差错】1、4月1日通知：遇到法诉用户协商还款，一二线：坐席无需谈判直接建单贷后，建单规范 贷后流程—协商还款—协商还款 （关键词 需贷后跟进），此通小结及工单类型错误；2、回电内容错误备注至工单处理结果处，应备注在工单内容\n【质检判罚】1、问题分类选择错误：客服未按客户问题场景选择合适准确的小结单分类或工单分类；2、关键信息记录错误-客服在工单内容/处理结果中，存在信息记录不准确的情况",
      "单句评论": "-",
      "日期": "2026-06-02",
      "差错类型": "问题分类选择错误",
      "差错描述": "1、4月1日通知：遇到法诉用户协商还款，一二线：坐席无需谈判直接建单贷后，建单规范 贷后流程—协商还款—协商还款 （关键词 需贷后跟进），此通小结及工单类型错误；2、回电内容错误备注至工单处理结果处，应备注在工单内容",
      "判罚内容": "1、问题分类选择错误：客服未按客户问题场景选择合适准确的小结单分类或工单分类；2、关键信息记录错误-客服在工单内容/处理结果中，存在信息记录不准确的情况"
    },
    {
      "姓名": "张思婕",
      "组别": "热线八组",
      "质检评分": 80,
      "最近复检时间": "2026-06-01",
      "场景": "投诉催收作业",
      "整单评论": "[2026-06-01 17:05:28]段林涛:【质检差错】客户进线咨询协商还款金额，无投诉催收诉求，坐席需按协商还款点选小结单建单，坐席错建投诉催收作业；\n【质检判罚】问题分类选择错误：客服未按客户问题场景选择合适准确的小结单分类或工单分类。若智能落单推荐的小结单或工单分类不准确，需手动选择符合客户问题场景的分类，直接选择推荐分类需扣罚",
      "单句评论": "-",
      "日期": "2026-06-01",
      "差错类型": "问题分类选择错误",
      "差错描述": "客户进线咨询协商还款金额，无投诉催收诉求，坐席需按协商还款点选小结单建单，坐席错建投诉催收作业；",
      "判罚内容": "问题分类选择错误：客服未按客户问题场景选择合适准确的小结单分类或工单分类。若智能落单推荐的小结单或工单分类不准确，需手动选择符合客户问题场景的分类，直接选择推荐分类需扣罚"
    },
    {
      "姓名": "张思婕",
      "组别": "热线八组",
      "质检评分": 80,
      "最近复检时间": "2026-06-01",
      "场景": "电话无声&无应答",
      "整单评论": "[2026-06-01 14:48:18]段林涛:【质检差错】客户进线核身客户明确报身份证号为：430624199112083619；坐席错误告知数字不对，数字的话不是18位；\n【质检判罚】解答错误：客户进线反馈的问题，客服错误处理或提供不准确的解决方案，导致未解决或未覆盖客户的问题；或未按照SOP准流程执行，处理不全/错误，包括但不限于：产品规则解答错误、政策条款解答错误、操作指引介绍错误及信息数据回复错误等",
      "单句评论": "[2026-06-01 14:44:16]刘倩:430624199112083619\n[2026-06-01 14:44:59]刘倩:4306241991\n[2026-06-01 14:45:10]刘倩:12083619",
      "日期": "2026-06-01",
      "差错类型": "解答错误",
      "差错描述": "客户进线核身客户明确报身份证号为：430624199112083619；坐席错误告知数字不对，数字的话不是18位；",
      "判罚内容": "解答错误：客户进线反馈的问题，客服错误处理或提供不准确的解决方案，导致未解决或未覆盖客户的问题；或未按照SOP准流程执行，处理不全/错误，包括但不限于：产品规则解答错误、政策条款解答错误、操作指引介绍错误及信息数据回复错误等"
    },
    {
      "姓名": "刘鑫",
      "组别": "热线四组",
      "质检评分": 80,
      "最近复检时间": "2026-06-02",
      "场景": "账单查询",
      "整单评论": "[2026-06-02 13:20:37]刘倩:【质检差错】新客，客户表示自己还款后多还款165的费用，客服告知已退回，小结单应该选择：结清账单费率不满。 \n【质检判罚】问题分类选择错误-客服未按客户问题场景选择合适准确的小结单分类或工单分类。",
      "单句评论": "-",
      "日期": "2026-06-02",
      "差错类型": "问题分类选择错误",
      "差错描述": "新客，客户表示自己还款后多还款165的费用，客服告知已退回，小结单应该选择：结清账单费率不满。",
      "判罚内容": "问题分类选择错误-客服未按客户问题场景选择合适准确的小结单分类或工单分类。"
    },
    {
      "姓名": "侯锐敏",
      "组别": "热线五组",
      "质检评分": 80,
      "最近复检时间": "2026-06-03",
      "场景": "催收业务咨询与办理",
      "整单评论": "[2026-06-03 16:57:37]王明卫:【质检差错】会话中逾期客户查询总欠款，坐席引导客户通过APP查询，客户询问坐席总欠款你看不到是吧，坐席回复是的，引导通过APP查看，解答错误，客户总欠款可以通过客服系统查询告知。\n【质检判罚】解答错误-解答错误：客户进线反馈的问题，客服错误处理或提供不准确的解决方案，导致未解决或未覆盖客户的问题；或未按照SOP准流程执行，处理不全/错误",
      "单句评论": "[2026-06-03 16:56:02]王明卫:解答错误",
      "日期": "2026-06-03",
      "差错类型": "解答错误",
      "差错描述": "会话中逾期客户查询总欠款，坐席引导客户通过APP查询，客户询问坐席总欠款你看不到是吧，坐席回复是的，引导通过APP查看，解答错误，客户总欠款可以通过客服系统查询告知。",
      "判罚内容": "解答错误-解答错误：客户进线反馈的问题，客服错误处理或提供不准确的解决方案，导致未解决或未覆盖客户的问题；或未按照SOP准流程执行，处理不全/错误"
    },
    {
      "姓名": "汤吉顺",
      "组别": "热线四组",
      "质检评分": 80,
      "最近复检时间": "2026-06-02",
      "场景": "未结清账单费率不满",
      "整单评论": "[2026-06-02 16:41:48]刘倩:【质检判罚】11:06:58（00:00:42）-11:07:10（00:00:54）长时间未回应。\n【质检判罚】响应不及时-时效规则：在线：非首触响应时效应在2min以内；热线：客户表述完问题及诉求后，电话沟通响应时效应在5s内给予回应",
      "单句评论": "[2026-06-02 16:41:30]刘倩:长时间未回应。",
      "日期": "2026-06-02",
      "差错类型": "响应不及时",
      "差错描述": "[2026-06-02 16:41:30]刘倩:长时间未回应。",
      "判罚内容": "11:06:58（00:00:42）-11:07:10（00:00:54）长时间未回应。\n【质检判罚】响应不及时-时效规则：在线：非首触响应时效应在2min以内；热线：客户表述完问题及诉求后，电话沟通响应时效应在5s内给予回应"
    },
    {
      "姓名": "梁金悦",
      "组别": "热线六组",
      "质检评分": 80,
      "最近复检时间": "2026-06-01",
      "场景": "其他权益卡咨询",
      "整单评论": "[2026-06-01 17:36:32]王明卫:【质检差错】客户进线查询会员开通记录，核实告知无记录，小结单三级类别可选择超级会员咨询，坐席错选其他权益卡咨询\n【质检判罚】问题分类选择错误-问题分类选择错误：客服未按客户问题场景选择合适准确的小结单分类或工单分类",
      "单句评论": "-",
      "日期": "2026-06-01",
      "差错类型": "问题分类选择错误",
      "差错描述": "客户进线查询会员开通记录，核实告知无记录，小结单三级类别可选择超级会员咨询，坐席错选其他权益卡咨询",
      "判罚内容": "问题分类选择错误-问题分类选择错误：客服未按客户问题场景选择合适准确的小结单分类或工单分类"
    },
    {
      "姓名": "吕星镇",
      "组别": "热线七组",
      "质检评分": 80,
      "最近复检时间": "2026-06-01",
      "场景": "征信上报规则",
      "整单评论": "[2026-06-01 18:31:40]刘倩:【质检差错】客户要求注销与重庆市黑卡小额贷款有限公司合作的循环贷账户，小结单应该选择：征信相关问题-征信问题咨询-小贷-征信上报规则。 【质检判罚】问题分类选择错误-客服未按客户问题场景选择合适准确的小结单分类或工单分类。",
      "单句评论": "-",
      "日期": "2026-06-01",
      "差错类型": "问题分类选择错误",
      "差错描述": "客户要求注销与重庆市黑卡小额贷款有限公司合作的循环贷账户，小结单应该选择：征信相关问题-征信问题咨询-小贷-征信上报规则。",
      "判罚内容": "问题分类选择错误-客服未按客户问题场景选择合适准确的小结单分类或工单分类。"
    },
    {
      "姓名": "杨雪",
      "组别": "热线四组",
      "质检评分": 80,
      "最近复检时间": "2026-06-01",
      "场景": "优惠券使用规则咨询",
      "整单评论": "[2026-06-01 17:21:23]王明卫:【质检差错】客户咨询京东E卡使用问题，沟通中坐席解释告知支付1元后，充值成功，1元会退回，解答错误\n【质检判罚】解答错误-解答错误：客户进线反馈的问题，客服错误处理或提供不准确的解决方案，导致未解决或未覆盖客户的问题；或未按照SOP准流程执行，处理不全/错误",
      "单句评论": "[2026-06-01 16:43:36]王明卫:1\n[2026-06-01 17:20:18]王明卫:解答错误",
      "日期": "2026-06-01",
      "差错类型": "解答错误",
      "差错描述": "客户咨询京东E卡使用问题，沟通中坐席解释告知支付1元后，充值成功，1元会退回，解答错误",
      "判罚内容": "解答错误-解答错误：客户进线反馈的问题，客服错误处理或提供不准确的解决方案，导致未解决或未覆盖客户的问题；或未按照SOP准流程执行，处理不全/错误"
    },
    {
      "姓名": "高行",
      "组别": "热线七组",
      "质检评分": 80,
      "最近复检时间": "2026-06-04",
      "场景": "-",
      "整单评论": "[2026-06-04 14:04:45]杨姿娇:【质检差错】点选仿冒电话/工作人员小结单，需按流程先询问客户是否已经添加对方微信，是否给对方提供验证码，然后根据客户回复的未加微信或已加微信流程进一步沟通处理，坐席遗漏关键步骤未询问客户是否添加微信、是否给对方提供验证码\n【质检判罚】遗漏关键步骤：客户反馈的问题，按照SOP需要多个步骤进行判断或处理，客服遗漏关键步骤",
      "单句评论": "[2026-06-04 09:19:02]杨姿娇:中介未加微",
      "日期": "2026-06-04",
      "差错类型": "遗漏关键步骤",
      "差错描述": "点选仿冒电话/工作人员小结单，需按流程先询问客户是否已经添加对方微信，是否给对方提供验证码，然后根据客户回复的未加微信或已加微信流程进一步沟通处理，坐席遗漏关键步骤未询问客户是否添加微信、是否给对方提供验证码",
      "判罚内容": "遗漏关键步骤：客户反馈的问题，按照SOP需要多个步骤进行判断或处理，客服遗漏关键步骤"
    },
    {
      "姓名": "刘艳",
      "组别": "热线六组",
      "质检评分": 80,
      "最近复检时间": "2026-06-04",
      "场景": "仿冒网址、电话或工作人员",
      "整单评论": "[2026-06-04 14:15:34]杨姿娇:【质检差错】客户2022/11/20已注销，2026/5/26进线反馈接到电话让处理逾期账单，小结应为恶意短信\n【质检判罚】问题分类选择错误：客服未按客户问题场景选择合适准确的小结单分类或工单分类",
      "单句评论": "[2026-06-04 09:55:14]杨姿娇:小结单错选",
      "日期": "2026-06-04",
      "差错类型": "问题分类选择错误",
      "差错描述": "客户2022/11/20已注销，2026/5/26进线反馈接到电话让处理逾期账单，小结应为恶意短信",
      "判罚内容": "问题分类选择错误：客服未按客户问题场景选择合适准确的小结单分类或工单分类"
    },
    {
      "姓名": "王兰兰",
      "组别": "热线六组",
      "质检评分": 80,
      "最近复检时间": "2026-06-04",
      "场景": "仿冒网址、电话或工作人员",
      "整单评论": "[2026-06-04 14:21:21]杨姿娇:【质检差错】客户进线要求不要给自己打电话了，对方说好分期有额度，让下载好分期，坐席直接告知是仿冒好分期的人员，提醒客户谨防诈骗；目前点选仿冒电话/工作人员小结单，需按流程先询问客户是否已经添加对方微信，是否给对方提供验证码，然后根据客户回复的未加微信或已加微信流程进一步沟通处理，坐席遗漏关键步骤未询问客户是否添加微信、是否给对方提供验证码\n【质检判罚】遗漏关键步骤：客户反馈的问题，按照SOP需要多个步骤进行判断或处理，客服遗漏关键步骤",
      "单句评论": "[2026-06-04 10:21:55]杨姿娇:中介未加微",
      "日期": "2026-06-04",
      "差错类型": "遗漏关键步骤",
      "差错描述": "客户进线要求不要给自己打电话了，对方说好分期有额度，让下载好分期，坐席直接告知是仿冒好分期的人员，提醒客户谨防诈骗；目前点选仿冒电话/工作人员小结单，需按流程先询问客户是否已经添加对方微信，是否给对方提供验证码，然后根据客户回复的未加微信或已加微信流程进一步沟通处理，坐席遗漏关键步骤未询问客户是否添加微信、是否给对方提供验证码",
      "判罚内容": "遗漏关键步骤：客户反馈的问题，按照SOP需要多个步骤进行判断或处理，客服遗漏关键步骤"
    },
    {
      "姓名": "胡鑫",
      "组别": "热线三组",
      "质检评分": 80,
      "最近复检时间": "2026-06-04",
      "场景": "仿冒网址、电话或工作人员",
      "整单评论": "[2026-06-04 14:34:41]杨姿娇:【质检差错】未注册/已注册账户未借款，收到逾期电话或短信，小结应为恶意短信\n【质检判罚】问题分类选择错误：客服未按客户问题场景选择合适准确的小结单分类或工单分类",
      "单句评论": "[2026-06-04 10:50:05]杨姿娇:小结单错选",
      "日期": "2026-06-04",
      "差错类型": "问题分类选择错误",
      "差错描述": "未注册/已注册账户未借款，收到逾期电话或短信，小结应为恶意短信",
      "判罚内容": "问题分类选择错误：客服未按客户问题场景选择合适准确的小结单分类或工单分类"
    },
    {
      "姓名": "鲁玉红",
      "组别": "热线八组",
      "质检评分": 80,
      "最近复检时间": "2026-06-01",
      "场景": "协商还款",
      "整单评论": "[2026-06-01 16:44:26]王琴:【质检差错】客户表示自己和贷后协商了还款方案，确认方案还款，此场景如客户未操作减免需按照按照协商还款流程沟通，无需升级贷后，坐席错误建单贷后\n【质检判罚】不应升但升/不应转但转-不应升但升：按业务 SOP 应自闭环场景，或不满足升级条件，客服错误升级",
      "单句评论": "-",
      "日期": "2026-06-01",
      "差错类型": "不应升但升/不应转但转",
      "差错描述": "客户表示自己和贷后协商了还款方案，确认方案还款，此场景如客户未操作减免需按照按照协商还款流程沟通，无需升级贷后，坐席错误建单贷后",
      "判罚内容": "不应升但升/不应转但转-不应升但升：按业务 SOP 应自闭环场景，或不满足升级条件，客服错误升级"
    },
    {
      "姓名": "雷海燕",
      "组别": "热线一组",
      "质检评分": 80,
      "最近复检时间": "2026-06-01",
      "场景": "临时特殊队列",
      "整单评论": "[2026-06-01 16:47:36]王琴:【质检差错】4月1日通知：遇到法诉用户协商还款，一二线：坐席无需谈判直接建单贷后，建单规范 贷后流程—协商还款—协商还款 （关键词 需贷后跟进）；如客户是诉前-确认与法诉的协商方案、诉中-诉前和解 结清后询问撤诉进度、诉后-法诉完成 汇款法院后询问结清进度，建单规范 贷后流程-其他-临时特殊列队-法诉用户（关键词） \n【质检判罚】问题分类选择错误：客服未按客户问题场景选择合适准确的小结单分类或工单分类",
      "单句评论": "-",
      "日期": "2026-06-01",
      "差错类型": "问题分类选择错误",
      "差错描述": "4月1日通知：遇到法诉用户协商还款，一二线：坐席无需谈判直接建单贷后，建单规范 贷后流程—协商还款—协商还款 （关键词 需贷后跟进）；如客户是诉前-确认与法诉的协商方案、诉中-诉前和解 结清后询问撤诉进度、诉后-法诉完成 汇款法院后询问结清进度，建单规范 贷后流程-其他-临时特殊列队-法诉用户（关键词）",
      "判罚内容": "问题分类选择错误：客服未按客户问题场景选择合适准确的小结单分类或工单分类"
    },
    {
      "姓名": "王瑜",
      "组别": "热线二组",
      "质检评分": 80,
      "最近复检时间": "2026-06-04",
      "场景": "仿冒网址、电话或工作人员",
      "整单评论": "[2026-06-04 14:23:35]王敏:【质检差错】客户言接到好分期营销电话说可以提额，坐席探寻是否400VIP专线，客户言不是，小结单点选仿冒，点选仿冒电话/工作人员小结单，需按流程先询问客户是否已经添加对方微信，是否给对方提供验证码，然后根据客户回复的未加微信或已加微信流程进一步沟通处理，坐席遗漏关键步骤未询问客户是否添加微信、是否给对方提供验证码\n【质检判罚】遗漏关键步骤：客户反馈的问题，按照SOP需要多个步骤进行判断或处理，客服遗漏关键步骤",
      "单句评论": "[2026-06-04 10:00:25]王敏:中介未加微",
      "日期": "2026-06-04",
      "差错类型": "遗漏关键步骤",
      "差错描述": "客户言接到好分期营销电话说可以提额，坐席探寻是否400VIP专线，客户言不是，小结单点选仿冒，点选仿冒电话/工作人员小结单，需按流程先询问客户是否已经添加对方微信，是否给对方提供验证码，然后根据客户回复的未加微信或已加微信流程进一步沟通处理，坐席遗漏关键步骤未询问客户是否添加微信、是否给对方提供验证码",
      "判罚内容": "遗漏关键步骤：客户反馈的问题，按照SOP需要多个步骤进行判断或处理，客服遗漏关键步骤"
    },
    {
      "姓名": "陈北仁",
      "组别": "热线七组",
      "质检评分": 80,
      "最近复检时间": "2026-06-01",
      "场景": "协商还款",
      "整单评论": "[2026-06-01 17:23:03]王琴:【质检差错】法诉客户进线确认与法诉的协商方案，小结单和工单类型应为临时特殊列队\n【质检判罚】问题分类选择错误：客服未按客户问题场景选择合适准确的小结单分类或工单分类",
      "单句评论": "-",
      "日期": "2026-06-01",
      "差错类型": "问题分类选择错误",
      "差错描述": "法诉客户进线确认与法诉的协商方案，小结单和工单类型应为临时特殊列队",
      "判罚内容": "问题分类选择错误：客服未按客户问题场景选择合适准确的小结单分类或工单分类"
    },
    {
      "姓名": "王靖",
      "组别": "热线八组",
      "质检评分": 80,
      "最近复检时间": "2026-06-04",
      "场景": "仿冒网址、电话或工作人员",
      "整单评论": "[2026-06-04 14:25:53]王敏:【质检差错】点选仿冒电话/工作人员小结单，需按流程先询问客户是否已经添加对方微信，是否给对方提供验证码，然后根据客户回复的未加微信或已加微信流程进一步沟通处理，坐席遗漏关键步骤未询问客户是否添加微信、是否给对方提供验证码\n【质检判罚】遗漏关键步骤：客户反馈的问题，按照SOP需要多个步骤进行判断或处理，客服遗漏关键步骤",
      "单句评论": "[2026-06-04 10:11:09]王敏:中介未加微",
      "日期": "2026-06-04",
      "差错类型": "遗漏关键步骤",
      "差错描述": "点选仿冒电话/工作人员小结单，需按流程先询问客户是否已经添加对方微信，是否给对方提供验证码，然后根据客户回复的未加微信或已加微信流程进一步沟通处理，坐席遗漏关键步骤未询问客户是否添加微信、是否给对方提供验证码",
      "判罚内容": "遗漏关键步骤：客户反馈的问题，按照SOP需要多个步骤进行判断或处理，客服遗漏关键步骤"
    },
    {
      "姓名": "刘越美",
      "组别": "热线四组",
      "质检评分": 80,
      "最近复检时间": "2026-06-04",
      "场景": "仿冒网址、电话或工作人员",
      "整单评论": "[2026-06-04 14:28:53]王敏:【质检差错】客户言接到好分期催收电话让还款，言语辱骂，坐席核实客户名下无好分期欠款，建议无需理会，此小结单应选恶意短信；不符合仿冒场景，点选错误\n【质检判罚】问题分类选择错误-客服未按客户问题场景选择合适准确的小结单分类或工单分类",
      "单句评论": "[2026-06-04 10:56:17]王敏:小结单错选",
      "日期": "2026-06-04",
      "差错类型": "问题分类选择错误",
      "差错描述": "客户言接到好分期催收电话让还款，言语辱骂，坐席核实客户名下无好分期欠款，建议无需理会，此小结单应选恶意短信；不符合仿冒场景，点选错误",
      "判罚内容": "问题分类选择错误-客服未按客户问题场景选择合适准确的小结单分类或工单分类"
    },
    {
      "姓名": "王瑜",
      "组别": "热线二组",
      "质检评分": 80,
      "最近复检时间": "2026-06-04",
      "场景": "仿冒网址、电话或工作人员",
      "整单评论": "[2026-06-04 14:32:07]王敏:【质检差错】点选仿冒电话/工作人员小结单，需按流程先询问客户是否已经添加对方微信，是否给对方提供验证码，然后根据客户回复的未加微信或已加微信流程进一步沟通处理，坐席遗漏关键步骤未询问客户是否添加微信、是否给对方提供验证码\n【质检判罚】遗漏关键步骤：客户反馈的问题，按照SOP需要多个步骤进行判断或处理，客服遗漏关键步骤",
      "单句评论": "[2026-06-04 11:11:30]王敏:中介未加微",
      "日期": "2026-06-04",
      "差错类型": "遗漏关键步骤",
      "差错描述": "点选仿冒电话/工作人员小结单，需按流程先询问客户是否已经添加对方微信，是否给对方提供验证码，然后根据客户回复的未加微信或已加微信流程进一步沟通处理，坐席遗漏关键步骤未询问客户是否添加微信、是否给对方提供验证码",
      "判罚内容": "遗漏关键步骤：客户反馈的问题，按照SOP需要多个步骤进行判断或处理，客服遗漏关键步骤"
    },
    {
      "姓名": "韩敏",
      "组别": "热线八组",
      "质检评分": 80,
      "最近复检时间": "2026-06-02",
      "场景": "投诉催收作业",
      "整单评论": "[2026-06-02 09:19:13]王琴:【质检差错】逾期催收问题坐席已处理，对扣款不满，逾期账单未划扣到待还款账单属于正常划扣，无需建单\n【质检判罚】不应升但升/不应转但转-不应升但升：按业务 SOP 应自闭环场景，或不满足升级条件，客服错误升级",
      "单句评论": "-",
      "日期": "2026-06-02",
      "差错类型": "不应升但升/不应转但转",
      "差错描述": "逾期催收问题坐席已处理，对扣款不满，逾期账单未划扣到待还款账单属于正常划扣，无需建单",
      "判罚内容": "不应升但升/不应转但转-不应升但升：按业务 SOP 应自闭环场景，或不满足升级条件，客服错误升级"
    },
    {
      "姓名": "张双娜",
      "组别": "热线一组",
      "质检评分": 80,
      "最近复检时间": "2026-06-04",
      "场景": "仿冒网址、电话或工作人员",
      "整单评论": "[2026-06-04 14:39:27]王敏:【质检差错】客户抱怨总是接到好分期推广营销电话要求屏蔽。并言之前已经多次投诉过了，坐席告知客户已屏蔽，客户认可，小结单可选投诉电销短信/电话，不符合仿冒场景，点选错误；\n【质检判罚】问题分类选择错误-客服未按客户问题场景选择合适准确的小结单分类或工单分类",
      "单句评论": "[2026-06-04 12:07:46]王敏:小结单错选",
      "日期": "2026-06-04",
      "差错类型": "问题分类选择错误",
      "差错描述": "客户抱怨总是接到好分期推广营销电话要求屏蔽。并言之前已经多次投诉过了，坐席告知客户已屏蔽，客户认可，小结单可选投诉电销短信/电话，不符合仿冒场景，点选错误；",
      "判罚内容": "问题分类选择错误-客服未按客户问题场景选择合适准确的小结单分类或工单分类"
    },
    {
      "姓名": "吴淑菡",
      "组别": "热线五组",
      "质检评分": 80,
      "最近复检时间": "2026-06-02",
      "场景": "临时特殊队列",
      "整单评论": "[2026-06-02 10:19:16]王琴:【质检差错】4月1日通知：遇到法诉用户协商还款，一二线：坐席无需谈判直接建单贷后，建单规范 贷后流程—协商还款—协商还款 （关键词 需贷后跟进）；如客户是诉前-确认与法诉的协商方案、诉中-诉前和解 结清后询问撤诉进度、诉后-法诉完成 汇款法院后询问结清进度，建单规范 贷后流程-其他-临时特殊列队-法诉用户（关键词） \n【质检判罚】问题分类选择错误：客服未按客户问题场景选择合适准确的小结单分类或工单分类",
      "单句评论": "-",
      "日期": "2026-06-02",
      "差错类型": "问题分类选择错误",
      "差错描述": "4月1日通知：遇到法诉用户协商还款，一二线：坐席无需谈判直接建单贷后，建单规范 贷后流程—协商还款—协商还款 （关键词 需贷后跟进）；如客户是诉前-确认与法诉的协商方案、诉中-诉前和解 结清后询问撤诉进度、诉后-法诉完成 汇款法院后询问结清进度，建单规范 贷后流程-其他-临时特殊列队-法诉用户（关键词）",
      "判罚内容": "问题分类选择错误：客服未按客户问题场景选择合适准确的小结单分类或工单分类"
    },
    {
      "姓名": "仝圆圆",
      "组别": "热线六组",
      "质检评分": 80,
      "最近复检时间": "2026-06-02",
      "场景": "临时特殊队列",
      "整单评论": "[2026-06-02 10:25:31]王琴:【质检差错】4月1日通知：遇到法诉用户协商还款，一二线：坐席无需谈判直接建单贷后，建单规范 贷后流程—协商还款—协商还款 （关键词 需贷后跟进）；如客户是诉前-确认与法诉的协商方案、诉中-诉前和解 结清后询问撤诉进度、诉后-法诉完成 汇款法院后询问结清进度，建单规范 贷后流程-其他-临时特殊列队-法诉用户（关键词） \n【质检判罚】问题分类选择错误：客服未按客户问题场景选择合适准确的小结单分类或工单分类",
      "单句评论": "-",
      "日期": "2026-06-02",
      "差错类型": "问题分类选择错误",
      "差错描述": "4月1日通知：遇到法诉用户协商还款，一二线：坐席无需谈判直接建单贷后，建单规范 贷后流程—协商还款—协商还款 （关键词 需贷后跟进）；如客户是诉前-确认与法诉的协商方案、诉中-诉前和解 结清后询问撤诉进度、诉后-法诉完成 汇款法院后询问结清进度，建单规范 贷后流程-其他-临时特殊列队-法诉用户（关键词）",
      "判罚内容": "问题分类选择错误：客服未按客户问题场景选择合适准确的小结单分类或工单分类"
    },
    {
      "姓名": "孙佳琦",
      "组别": "热线一组",
      "质检评分": 80,
      "最近复检时间": "2026-06-04",
      "场景": "仿冒网址、电话或工作人员",
      "整单评论": "[2026-06-04 14:46:22]王敏:【质检差错】客户言接到自称好分期的说可以线下放款，坐席告知无此业务，且告知电销电话之前已在系统屏蔽了，点选仿冒电话/工作人员小结单，需按流程先询问客户是否已经添加对方微信，是否给对方提供验证码，然后根据客户回复的未加微信或已加微信流程进一步沟通处理，坐席遗漏关键步骤未询问客户是否添加微信、是否给对方提供验证码等\n【质检判罚】遗漏关键步骤：客户反馈的问题，按照SOP需要多个步骤进行判断或处理，客服遗漏关键步骤",
      "单句评论": "[2026-06-04 12:19:17]王敏:中介未加微",
      "日期": "2026-06-04",
      "差错类型": "遗漏关键步骤",
      "差错描述": "客户言接到自称好分期的说可以线下放款，坐席告知无此业务，且告知电销电话之前已在系统屏蔽了，点选仿冒电话/工作人员小结单，需按流程先询问客户是否已经添加对方微信，是否给对方提供验证码，然后根据客户回复的未加微信或已加微信流程进一步沟通处理，坐席遗漏关键步骤未询问客户是否添加微信、是否给对方提供验证码等",
      "判罚内容": "遗漏关键步骤：客户反馈的问题，按照SOP需要多个步骤进行判断或处理，客服遗漏关键步骤"
    },
    {
      "姓名": "卜浩",
      "组别": "热线五组",
      "质检评分": 80,
      "最近复检时间": "2026-06-02",
      "场景": "临时特殊队列",
      "整单评论": "[2026-06-02 10:59:04]王琴:【质检差错】4月1日通知：遇到法诉用户协商还款，一二线：坐席无需谈判直接建单贷后，建单规范 贷后流程—协商还款—协商还款 （关键词 需贷后跟进）；如客户是诉前-确认与法诉的协商方案、诉中-诉前和解 结清后询问撤诉进度、诉后-法诉完成 汇款法院后询问结清进度，建单规范 贷后流程-其他-临时特殊列队-法诉用户（关键词） \n【质检判罚】问题分类选择错误：客服未按客户问题场景选择合适准确的小结单分类或工单分类",
      "单句评论": "-",
      "日期": "2026-06-02",
      "差错类型": "问题分类选择错误",
      "差错描述": "4月1日通知：遇到法诉用户协商还款，一二线：坐席无需谈判直接建单贷后，建单规范 贷后流程—协商还款—协商还款 （关键词 需贷后跟进）；如客户是诉前-确认与法诉的协商方案、诉中-诉前和解 结清后询问撤诉进度、诉后-法诉完成 汇款法院后询问结清进度，建单规范 贷后流程-其他-临时特殊列队-法诉用户（关键词）",
      "判罚内容": "问题分类选择错误：客服未按客户问题场景选择合适准确的小结单分类或工单分类"
    }
  ],
  "scene_stats": {
    "其他还款方式咨询": 1,
    "协商还款": 11,
    "逾期客户延期还款": 1,
    "结清账单费率不满": 5,
    "超级会员取消": 7,
    "好借卡取消": 3,
    "好借卡咨询": 1,
    "投诉催收作业": 3,
    "-": 4,
    "催收投诉安抚": 5,
    "未结清账单费率不满": 7,
    "账单查询": 8,
    "提前还款或结清咨询": 1,
    "降费卡取消": 4,
    "未逾期协商还款": 1,
    "结清证明申请": 1,
    "征信上报规则": 2,
    "调取合同申请": 1,
    "营销活动咨询": 1,
    "开具发票申请": 1,
    "临时特殊队列": 7,
    "当期还款办理": 1,
    "超级会员咨询": 1,
    "电话无声&无应答": 2,
    "催收业务咨询与办理": 1,
    "其他权益卡咨询": 1,
    "优惠券使用规则咨询": 1,
    "仿冒网址、电话或工作人员": 9
  },
  "week_stats": {
    "W1": 91
  },
  "heat_data": {
    "热线三组": {
      "其他还款方式咨询": 1,
      "逾期客户延期还款": 1,
      "催收投诉安抚": 4,
      "未结清账单费率不满": 2,
      "协商还款": 3,
      "超级会员取消": 1,
      "结清证明申请": 1,
      "账单查询": 1,
      "临时特殊队列": 1,
      "结清账单费率不满": 1,
      "超级会员咨询": 1,
      "仿冒网址、电话或工作人员": 1
    },
    "热线五组": {
      "协商还款": 1,
      "结清账单费率不满": 3,
      "账单查询": 2,
      "超级会员取消": 1,
      "调取合同申请": 1,
      "好借卡取消": 1,
      "电话无声&无应答": 1,
      "临时特殊队列": 3,
      "催收业务咨询与办理": 1
    },
    "热线八组": {
      "超级会员取消": 1,
      "好借卡取消": 1,
      "-": 1,
      "催收投诉安抚": 1,
      "提前还款或结清咨询": 1,
      "未逾期协商还款": 1,
      "账单查询": 1,
      "降费卡取消": 1,
      "临时特殊队列": 1,
      "投诉催收作业": 2,
      "电话无声&无应答": 1,
      "协商还款": 1,
      "仿冒网址、电话或工作人员": 1
    },
    "热线一组": {
      "协商还款": 1,
      "超级会员取消": 1,
      "临时特殊队列": 1,
      "仿冒网址、电话或工作人员": 2
    },
    "热线四组": {
      "协商还款": 3,
      "账单查询": 1,
      "未结清账单费率不满": 1,
      "优惠券使用规则咨询": 1,
      "仿冒网址、电话或工作人员": 1
    },
    "热线六组": {
      "好借卡咨询": 1,
      "账单查询": 2,
      "结清账单费率不满": 1,
      "降费卡取消": 2,
      "征信上报规则": 1,
      "超级会员取消": 1,
      "开具发票申请": 1,
      "未结清账单费率不满": 1,
      "好借卡取消": 1,
      "当期还款办理": 1,
      "-": 1,
      "其他权益卡咨询": 1,
      "仿冒网址、电话或工作人员": 2,
      "临时特殊队列": 1
    },
    "热线二组": {
      "投诉催收作业": 1,
      "未结清账单费率不满": 1,
      "仿冒网址、电话或工作人员": 2
    },
    "热线七组": {
      "超级会员取消": 2,
      "降费卡取消": 1,
      "账单查询": 1,
      "未结清账单费率不满": 2,
      "协商还款": 2,
      "营销活动咨询": 1,
      "-": 2,
      "征信上报规则": 1
    }
  }
}